[
  {
    "type": "item_group",
    "subtype": "collection",
    "//": "default zombie children clothing (always), additional items from child_items (sometimes)",
    "id": "default_zombie_children_death_drops",
    "entries": [
      { "group": "default_zombie_children_clothes", "damage": [ 1, 4 ], "custom-flags": [ "UNDERSIZE" ] },
      { "group": "child_items", "prob": 65 }
    ]
  },
  {
    "type": "item_group",
    "subtype": "collection",
    "//": "contains cloth for an average zombie child",
    "id": "default_zombie_children_clothes",
    "entries": [
      { "group": "coats_unisex", "prob": 20 },
      { "group": "common_gloves", "prob": 20 },
      { "group": "hatstore_hats", "prob": 20 },
      { "group": "scarfs_unisex", "prob": 20 },
      {
        "distribution": [
          { "item": "backpack", "prob": 50 },
          { "item": "slingpack", "prob": 25 },
          { "item": "travelpack", "prob": 20 },
          { "item": "petpack", "prob": 5 }
        ],
        "prob": 25
      },
      { "group": "accesories_personal_unisex_kids", "prob": 15, "count": 2 },
      {
        "distribution": [
          {
            "collection": [
              {
                "distribution": [
                  { "group": "male_underwear", "prob": 90 },
                  { "item": "union_suit", "prob": 10 }
                ]
              },
              {
                "distribution": [
                  {
                    "collection": [
                      { "group": "pants_male", "prob": 60 },
                      { "group": "shirts_unisex", "prob": 60 },
                      { "item": "leather_belt", "prob": 30 }
                    ]
                  },
                  { "item": "suit", "prob": 5 },
                  { "item": "tux", "prob": 5 }
                ]
              },
              { "group": "neckties", "prob": 15 },
              { "group": "shoes_unisex", "prob": 30 },
              { "group": "socks_unisex", "prob": 50 }
            ]
          },
          {
            "collection": [
              { "group": "female_underwear", "prob": 90 },
              {
                "distribution": [
                  {
                    "collection": [
                      { "group": "pants_female", "prob": 60 },
                      { "group": "shoes_unisex", "prob": 30 },
                      { "group": "shirts_unisex", "prob": 60 },
                      {
                        "distribution": [
                          {
                            "distribution": [
                              { "item": "stockings", "prob": 40 },
                              { "item": "stockings_wool", "prob": 10 },
                              { "item": "tights", "prob": 50 }
                            ]
                          },
                          { "group": "socks_unisex", "prob": 50 }
                        ]
                      }
                    ],
                    "prob": 80
                  },
                  {
                    "collection": [
                      {
                        "distribution": [ { "item": "dress", "prob": 70 }, { "item": "sundress", "prob": 50 } ]
                      },
                      { "group": "dress_shoes", "prob": 30 },
                      {
                        "distribution": [
                          { "item": "stockings", "prob": 40 },
                          { "item": "stockings_wool", "prob": 10 },
                          { "item": "tights", "prob": 50 }
                        ]
                      }
                    ],
                    "prob": 20
                  }
                ]
              }
            ]
          }
        ]
      }
    ]
  }
]
