[
  {
    "id": "trex_gun",
    "copy-from": "rifle_1shot",
    "type": "GUN",
    "name": { "str": "Elephant gun" },
    "description": "A ornately engraved, custom-made double rifle specially designed for the hunting of huge game.  You could obviously kill everything with this, EVERYTHING.  If you ever find enough ammo of course.",
    "weight": "8082 g",
    "volume": "3 L",
    "price": 2000000,
    "price_postapoc": 5000,
    "to_hit": 1,
    "material": [ "steel", "wood" ],
    "color": "light_blue",
    "ammo": "700nx",
    "dispersion": 90,
    "clip_size": 2,
    "reload": 300,
    "barrel_length": "1000 ml",
    "valid_mod_locations": [
      [ "accessories", 4 ],
      [ "grip", 1 ],
      [ "mechanism", 4 ],
      [ "muzzle", 1 ],
      [ "rail", 1 ],
      [ "sights", 1 ],
      [ "sling", 1 ],
      [ "stock", 1 ],
      [ "underbarrel", 1 ]
    ],
    "extend": { "flags": [ "RELOAD_ONE" ] }
  }
]
