[
  {
    "type": "mod_tileset",
    "compatibility": [ "UNDEAD_PEOPLE_BASE", "UNDEAD_PEOPLE", "MshockRealXotto", "MSX++DEAD_PEOPLE" ],
    "tiles-new": [
      {
        "file": "MagicalNights_Misc.png",
        "tiles": [
          { "id": "bg_shadow_frog", "fg": 1, "rotates": false },
          { "id": "bg_shadow_goblin", "fg": 2, "rotates": false },
          { "id": "bg_shadow_item", "fg": 3, "rotates": false },
          { "id": "bg_shadow_normal", "fg": 4, "rotates": false },
          { "id": "overlay_mutation_bio_sneeze_beam", "fg": 5, "rotates": false },
          { "id": "overlay_mutation_DRAGON_FEET", "fg": 6 },
          { "id": "overlay_mutation_DRAGON_MAW_BLACK", "fg": 7 },
          { "id": "overlay_female_mutation_DRAGON_SCALES_BLACK", "fg": 8 },
          { "id": "overlay_male_mutation_DRAGON_SCALES_BLACK", "fg": 9 },
          { "id": "overlay_mutation_DRAGON_TAIL", "fg": 10 },
          { "id": "overlay_mutation_DRAGON_TAIL_SCALED", "fg": 11 },
          { "id": "overlay_mutation_DRAGON_TALONS_BLACK", "fg": 12, "rotates": false },
          { "id": "overlay_mutation_DRAGON_WINGS_BLACK", "fg": 13 },
          { "id": "overlay_mutation_MUZZLE_DRAGON", "fg": 14 },
          { "id": "overlay_mutation_SCALED_HANDS", "fg": 15, "rotates": false },
          { "id": "f_null", "fg": 16, "rotates": false },
          { "id": "mon_null", "fg": 16, "rotates": false },
          { "id": "null", "fg": 16, "rotates": false },
          { "id": "t_null", "fg": 16, "rotates": false },
          { "id": "vp_null", "fg": 16, "rotates": false },
          { "id": "fd_clairvoyant", "fg": 16, "rotates": false },
          { "id": "fd_darkness", "fg": 16, "rotates": false },
          { "id": "fd_fright", "fg": 16, "rotates": false },
          { "id": "fd_vault_atmosphere", "fg": 16, "rotates": false },
          { "id": "soul_burn_item", "fg": 16, "rotates": false },
          {
            "id": "vp_folding_orichalcum_frame",
            "fg": 17,
            "rotates": false,
            "multitile": true,
            "additional_tiles": [ { "id": "broken", "fg": 18 } ]
          },
          {
            "id": "vp_frame_orichalcum_cover",
            "fg": 19,
            "rotates": false,
            "multitile": true,
            "additional_tiles": [ { "id": "broken", "fg": 20 } ]
          },
          {
            "id": "vp_frame_orichalcum_cross",
            "fg": 21,
            "rotates": true,
            "multitile": true,
            "additional_tiles": [ { "id": "broken", "fg": 22 } ]
          },
          {
            "id": "vp_frame_orichalcum_horizontal",
            "fg": 23,
            "rotates": false,
            "multitile": true,
            "additional_tiles": [ { "id": "broken", "fg": 24 } ]
          },
          {
            "id": "vp_frame_orichalcum_horizontal_2",
            "fg": 25,
            "rotates": false,
            "multitile": true,
            "additional_tiles": [ { "id": "broken", "fg": 26 } ]
          },
          {
            "id": "vp_frame_orichalcum_ne",
            "fg": 27,
            "rotates": false,
            "multitile": true,
            "additional_tiles": [ { "id": "broken", "fg": 28 } ]
          },
          {
            "id": "vp_frame_orichalcum_nw",
            "fg": 29,
            "rotates": false,
            "multitile": true,
            "additional_tiles": [ { "id": "broken", "fg": 30 } ]
          },
          {
            "id": "vp_frame_orichalcum_se",
            "fg": 31,
            "rotates": false,
            "multitile": true,
            "additional_tiles": [ { "id": "broken", "fg": 32 } ]
          },
          {
            "id": "vp_frame_orichalcum_sw",
            "fg": 33,
            "rotates": false,
            "multitile": true,
            "additional_tiles": [ { "id": "broken", "fg": 34 } ]
          },
          {
            "id": "vp_frame_orichalcum_vertical",
            "fg": 35,
            "rotates": false,
            "multitile": true,
            "additional_tiles": [ { "id": "broken", "fg": 36 } ]
          },
          {
            "id": "vp_frame_orichalcum_vertical_2",
            "fg": 37,
            "rotates": false,
            "multitile": true,
            "additional_tiles": [ { "id": "broken", "fg": 38 } ]
          }
        ],
        "//": "range 1 to 256",
        "sprite_width": 32,
        "sprite_height": 32,
        "sprite_offset_x": 0,
        "sprite_offset_y": 0
      },
      {
        "file": "MagicalNights_Tiles.png",
        "tiles": [
          {
            "id": "t_dirtfloor",
            "fg": [
              { "weight": 1, "sprite": 258 },
              { "weight": 1, "sprite": 259 },
              { "weight": 1, "sprite": 260 },
              { "weight": 1, "sprite": 261 },
              { "weight": 1, "sprite": 262 }
            ],
            "rotates": false
          },
          { "id": "f_altar", "fg": 263, "rotates": false },
          { "id": "f_attunement_altar", "fg": 264, "rotates": false },
          { "id": "f_demon_forge", "fg": 265 },
          { "id": "f_magiclysm_translocator_gate", "fg": 266 },
          {
            "id": "f_magic_bench",
            "fg": 267,
            "rotates": true,
            "multitile": true,
            "additional_tiles": [
              { "id": "center", "fg": 268 },
              { "id": "corner", "fg": [ 269, 270, 271, 272 ] },
              { "id": "edge", "fg": [ 273, 274 ] },
              { "id": "end_piece", "fg": [ 275, 276, 277, 278 ] },
              { "id": "t_connection", "fg": [ 279, 280, 281, 282 ] },
              { "id": "unconnected", "fg": [ 283, 283, 283, 283 ] }
            ]
          },
          { "id": "f_magic_circle", "fg": 284, "rotates": false },
          {
            "id": [
              "attunement_altar_NW",
              "attunement_altar_NE",
              "attunement_altar_SW",
              "attunement_altar_SE",
              "attunement_altar_NW_roof",
              "attunement_altar_NE_roof",
              "attunement_altar_SW_roof",
              "attunement_altar_SE_roof"
            ],
            "fg": 285,
            "rotates": false
          },
          {
            "id": [ "black_dragon_lair_z-0_NW", "black_dragon_lair_z-0_NE", "black_dragon_lair_z-0_SW", "black_dragon_lair_z-0_SE" ],
            "fg": 286,
            "rotates": false
          },
          {
            "id": [
              "black_dragon_lair_z-1_NW",
              "black_dragon_lair_z-1_NE",
              "black_dragon_lair_z-1_SW",
              "black_dragon_lair_z-1_SE",
              "black_dragon_lair_z-2_NW",
              "black_dragon_lair_z-2_NE",
              "black_dragon_lair_z-2_SW",
              "black_dragon_lair_z-2_SE",
              "black_dragon_lair_z-3_NW",
              "black_dragon_lair_z-3_NE",
              "black_dragon_lair_z-3_SW",
              "black_dragon_lair_z-3_SE",
              "black_dragon_lair_z-4_NW",
              "black_dragon_lair_z-4_NE",
              "black_dragon_lair_z-4_SW",
              "black_dragon_lair_z-4_SE"
            ],
            "fg": 287,
            "rotates": false
          },
          { "id": [ "demon_spider_lair" ], "fg": 288, "rotates": false },
          { "id": [ "forest_tomb", "forest_tomb_roof" ], "fg": 289, "rotates": false },
          { "id": [ "forest_tomb_bottom" ], "fg": 290, "rotates": false },
          {
            "id": [
              "forge_1A",
              "forge_2A",
              "forge_3A",
              "forge_4A",
              "forge_5A",
              "forge_1B",
              "forge_2B",
              "forge_3B",
              "forge_4B",
              "forge_5B"
            ],
            "fg": 291,
            "rotates": false
          },
          { "id": [ "goblin_camp" ], "fg": 292, "rotates": false },
          { "id": [ "magic_cabin" ], "fg": 293, "rotates": false },
          { "id": [ "magic_shop", "magic_shop_2ndfloor", "magic_shop_roof" ], "fg": 294, "rotates": false },
          { "id": [ "orc_village" ], "fg": 295, "rotates": false },
          { "id": "wizardtower1_ground", "fg": 296, "rotates": false },
          {
            "id": "t_dirt_barren",
            "fg": [
              { "weight": 40, "sprite": 297 },
              { "weight": 40, "sprite": 298 },
              { "weight": 40, "sprite": 299 },
              { "weight": 40, "sprite": 300 },
              { "weight": 1, "sprite": 301 }
            ],
            "rotates": false
          },
          { "id": "t_magiconc_floor", "fg": 302, "rotates": false },
          { "id": "t_webbed_corpse", "fg": 303, "rotates": false },
          {
            "id": "t_demon_web_wall",
            "fg": 304,
            "bg": 257,
            "rotates": true,
            "multitile": true,
            "additional_tiles": [
              { "id": "center", "fg": 305, "bg": 257 },
              { "id": "corner", "fg": [ 306, 307, 308, 309 ], "bg": 257 },
              { "id": "edge", "fg": [ 310, 311 ], "bg": 257 },
              { "id": "end_piece", "fg": [ 312, 313, 314, 315 ], "bg": 257 },
              { "id": "t_connection", "fg": [ 316, 317, 318, 319 ], "bg": 257 },
              { "id": "unconnected", "fg": 320, "bg": 257 }
            ]
          },
          { "id": "tr_magic_door", "fg": 321, "rotates": false },
          { "id": "tr_bear", "fg": 322, "rotates": false },
          { "id": "tr_forge_vault", "fg": 323, "rotates": false }
        ],
        "//": "range 257 to 512",
        "sprite_width": 32,
        "sprite_height": 32,
        "sprite_offset_x": 0,
        "sprite_offset_y": 0
      },
      {
        "file": "MagicalNights_Items.png",
        "tiles": [
          { "id": "bio_fuel_cell_blood", "fg": 513, "bg": 3, "rotates": false },
          { "id": "overlay_wielded_bio_fuel_cell_blood", "fg": 513, "rotates": false },
          { "id": "bio_sneeze_beam", "fg": 514, "bg": 3, "rotates": false },
          { "id": "overlay_wielded_bio_sneeze_beam", "fg": 514, "rotates": false },
          { "id": "adrenal_gland_large", "fg": 515, "rotates": false },
          { "id": "overlay_wielded_adrenal_gland_large", "fg": 515, "rotates": false },
          { "id": "alumentum", "fg": 516, "rotates": false },
          { "id": "overlay_wielded_alumentum", "fg": 516, "rotates": false },
          { "id": "bulette_pearl", "fg": 517, "rotates": false },
          { "id": "overlay_wielded_bulette_pearl", "fg": 517, "rotates": false },
          { "id": "bulette_plate", "fg": 518, "rotates": false },
          { "id": "overlay_wielded_bulette_plate", "fg": 518, "rotates": false },
          { "id": "vp_bulette_plate", "fg": 519, "rotates": false },
          { "id": "copper_circlet", "fg": 520, "rotates": false },
          { "id": "overlay_wielded_copper_circlet", "fg": 520, "rotates": false },
          { "id": "overlay_worn_copper_circlet", "fg": 521, "rotates": false },
          { "id": "copper_infuser", "fg": 522, "rotates": false },
          { "id": "overlay_wielded_copper_infuser", "fg": 522, "rotates": false },
          { "id": "overlay_worn_copper_infuser", "fg": 523, "rotates": false },
          { "id": "demon_chitin_piece", "fg": 524, "rotates": false },
          { "id": "overlay_wielded_demon_chitin_piece", "fg": 524, "rotates": false },
          { "id": "demon_chitin_plate", "fg": 525, "rotates": false },
          { "id": "overlay_wielded_demon_chitin_plate", "fg": 525, "rotates": false },
          { "id": "demon_spider_fang", "fg": 526, "rotates": false },
          { "id": "overlay_wielded_demon_spider_fang", "fg": 526, "rotates": false },
          { "id": "dragon_essence", "fg": 527, "rotates": false },
          { "id": "overlay_wielded_dragon_essence", "fg": 527, "rotates": false },
          { "id": "glow_dust", "fg": 528 },
          { "id": "overlay_wielded_glow_dust", "fg": 528 },
          { "id": "glow_light", "fg": 529, "rotates": false },
          { "id": "overlay_wielded_glow_light", "fg": 529, "rotates": false },
          { "id": "glow_light_off", "fg": 530, "rotates": false },
          { "id": "overlay_wielded_glow_light_off", "fg": 530, "rotates": false },
          { "id": "overlay_wielded_owlbear_stone", "fg": 531 },
          { "id": "owlbear_stone", "fg": 531 },
          { "id": "overlay_wielded_potion_starter", "fg": 532 },
          { "id": "potion_starter", "fg": 532 },
          { "id": "overlay_wielded_silver_infuser", "fg": 533, "rotates": false },
          { "id": "silver_infuser", "fg": 533, "rotates": false },
          { "id": "overlay_worn_silver_infuser", "fg": 534, "rotates": false },
          { "id": "overlay_wielded_stirge_proboscis", "fg": 535, "rotates": false },
          { "id": "stirge_proboscis", "fg": 535, "rotates": false },
          { "id": "overlay_wielded_stone_shell", "fg": 536 },
          { "id": "stone_shell", "fg": 536 },
          { "id": "blood", "fg": 537, "rotates": false },
          { "id": "overlay_wielded_blood", "fg": 537, "rotates": false },
          { "id": "dragon_blood", "fg": 538, "rotates": false },
          { "id": "overlay_wielded_dragon_blood", "fg": 538, "rotates": false },
          { "id": "overlay_wielded_tainted_blood", "fg": 539, "rotates": false },
          { "id": "tainted_blood", "fg": 539, "rotates": false },
          { "id": "arrow_odin", "fg": 540, "rotates": false },
          { "id": "overlay_wielded_arrow_odin", "fg": 540, "rotates": false },
          { "id": "ichaival", "fg": 541, "rotates": false },
          { "id": "overlay_wielded_ichaival", "fg": 542, "rotates": false },
          { "id": "overlay_wielded_quiver", "fg": 543, "rotates": false },
          { "id": "quiver", "fg": 543, "bg": 3, "rotates": false },
          { "id": "overlay_worn_quiver", "fg": 544, "rotates": false },
          { "id": "overlay_wielded_quiver_birchbark", "fg": 545, "rotates": false },
          { "id": "quiver_birchbark", "fg": 545, "bg": 3, "rotates": false },
          { "id": "overlay_worn_quiver_birchbark", "fg": 546, "rotates": false },
          { "id": "overlay_wielded_quiver_large_birchbark", "fg": 547, "rotates": false },
          { "id": "quiver_large_birchbark", "fg": 547, "bg": 3, "rotates": false },
          { "id": "overlay_worn_quiver_large_birchbark", "fg": 548, "rotates": false },
          { "id": "black_dragon_hide_raw", "fg": 549, "rotates": false },
          { "id": "overlay_wielded_black_dragon_hide_raw", "fg": 549, "rotates": false },
          { "id": "black_dragon_tanned_hide", "fg": 550, "rotates": false },
          { "id": "overlay_wielded_black_dragon_tanned_hide", "fg": 550, "rotates": false },
          { "id": "black_dragon_tanning_hide", "fg": 551, "rotates": false },
          { "id": "overlay_wielded_black_dragon_tanning_hide", "fg": 551, "rotates": false },
          { "id": "boots_black_dragon_hide", "fg": 552, "rotates": false },
          { "id": "overlay_wielded_boots_black_dragon_hide", "fg": 552, "rotates": false },
          { "id": "overlay_worn_boots_black_dragon_hide", "fg": 553, "rotates": false },
          { "id": "boots_black_dragon_scale", "fg": 554, "rotates": false },
          { "id": "overlay_wielded_boots_black_dragon_scale", "fg": 554, "rotates": false },
          { "id": "overlay_worn_boots_black_dragon_scale", "fg": 555, "rotates": false },
          { "id": "boots_xlblack_dragon_hide", "fg": 556, "rotates": false },
          { "id": "overlay_wielded_boots_xlblack_dragon_hide", "fg": 556, "rotates": false },
          { "id": "boots_xlblack_dragon_scale", "fg": 557, "rotates": false },
          { "id": "overlay_wielded_boots_xlblack_dragon_scale", "fg": 557, "rotates": false },
          { "id": "dragon_black_scale", "fg": 558, "rotates": false },
          { "id": "overlay_wielded_dragon_black_scale", "fg": 559, "rotates": false },
          { "id": "gauntlets_black_dragon_scale", "fg": 559, "rotates": false },
          { "id": "overlay_wielded_gauntlets_black_dragon_scale", "fg": 559, "rotates": false },
          { "id": "overlay_worn_gauntlets_black_dragon_scale", "fg": 560, "rotates": false },
          { "id": "gauntlets_xlblack_dragon_scale", "fg": 561, "rotates": false },
          { "id": "overlay_wielded_gauntlets_xlblack_dragon_scale", "fg": 561, "rotates": false },
          { "id": "gloves_black_dragon_hide", "fg": 562, "rotates": false },
          { "id": "overlay_wielded_gloves_black_dragon_hide", "fg": 562, "rotates": false },
          { "id": "overlay_worn_gloves_black_dragon_hide", "fg": 564, "rotates": false },
          { "id": "gloves_xlblack_dragon_hide", "fg": 564, "rotates": false },
          { "id": "overlay_wielded_gloves_xlblack_dragon_hide", "fg": 564, "rotates": false },
          { "id": "helmet_black_dragon_hide", "fg": 565, "rotates": false },
          { "id": "overlay_wielded_helmet_black_dragon_hide", "fg": 565, "rotates": false },
          { "id": "overlay_worn_helmet_black_dragon_hide", "fg": 566, "rotates": false },
          { "id": "helmet_black_dragon_scale", "fg": 567, "rotates": false },
          { "id": "overlay_wielded_helmet_black_dragon_scale", "fg": 567, "rotates": false },
          { "id": "overlay_worn_helmet_black_dragon_scale", "fg": 568, "rotates": false },
          { "id": "helmet_xlblack_dragon_hide", "fg": 569, "rotates": false },
          { "id": "overlay_wielded_helmet_xlblack_dragon_hide", "fg": 569, "rotates": false },
          { "id": "helmet_xlblack_dragon_scale", "fg": 570, "rotates": false },
          { "id": "overlay_wielded_helmet_xlblack_dragon_scale", "fg": 570, "rotates": false },
          { "id": "overlay_wielded_suit_black_dragon_hide", "fg": 571, "rotates": false },
          { "id": "suit_black_dragon_hide", "fg": 571, "rotates": false },
          { "id": "overlay_worn_suit_black_dragon_hide", "fg": 572, "rotates": false },
          { "id": "overlay_wielded_suit_black_dragon_scale", "fg": 573, "rotates": false },
          { "id": "suit_black_dragon_scale", "fg": 573, "rotates": false },
          { "id": "overlay_worn_suit_black_dragon_scale", "fg": 574, "rotates": false },
          { "id": "overlay_wielded_suit_xlblack_dragon_hide", "fg": 755, "rotates": false },
          { "id": "suit_xlblack_dragon_hide", "fg": 575, "rotates": false },
          { "id": "overlay_wielded_suit_xlblack_dragon_scale", "fg": 756, "rotates": false },
          { "id": "suit_xlblack_dragon_scale", "fg": 576, "rotates": false },
          { "id": "lair_map", "fg": 577, "rotates": false },
          { "id": "overlay_wielded_lair_map", "fg": 577, "rotates": false },
          { "id": "overlay_wielded_retreat_map", "fg": 578, "rotates": false },
          { "id": "retreat_map", "fg": 578, "rotates": false },
          { "id": "overlay_wielded_wizard_photo", "fg": 579, "rotates": false },
          { "id": "wizard_photo", "fg": 579, "rotates": false },
          { "id": "animist_doll_decayed_pouncer", "fg": 580, "rotates": false },
          { "id": "overlay_wielded_animist_doll_decayed_pouncer", "fg": 581, "rotates": false },
          { "id": "animist_doll_skeleton", "fg": 582, "rotates": false },
          { "id": "overlay_wielded_animist_doll_skeleton", "fg": 583, "rotates": false },
          { "id": "animist_doll_zombie", "fg": 584, "rotates": false },
          { "id": "overlay_wielded_animist_doll_zombie", "fg": 585, "rotates": false },
          { "id": "cats_grace_potion", "fg": 586 },
          { "id": "overlay_wielded_cats_grace_potion", "fg": 586 },
          { "id": "eagles_sight_potion", "fg": 587 },
          { "id": "overlay_wielded_eagles_sight_potion", "fg": 587 },
          { "id": "foxs_cunning_potion", "fg": 588 },
          { "id": "overlay_wielded_foxs_cunning_potion", "fg": 588 },
          { "id": "mana_potion", "fg": 589, "rotates": false },
          { "id": "overlay_wielded_mana_potion", "fg": 589, "rotates": false },
          { "id": "mana_potion_greater", "fg": 590, "rotates": false },
          { "id": "overlay_wielded_mana_potion_greater", "fg": 590, "rotates": false },
          { "id": "mana_potion_lesser", "fg": 591, "rotates": false },
          { "id": "overlay_wielded_mana_potion_lesser", "fg": 591, "rotates": false },
          { "id": "ogres_strength_potion", "fg": 592 },
          { "id": "overlay_wielded_ogres_strength_potion", "fg": 592 },
          { "id": "overlay_wielded_twisted_restore_potion", "fg": 593, "rotates": false },
          { "id": "twisted_restore_potion", "fg": 593, "rotates": false },
          { "id": "overlay_wielded_twisted_restore_potion_improved", "fg": 594, "rotates": false },
          { "id": "twisted_restore_potion_improved", "fg": 594, "rotates": false },
          { "id": "overlay_wielded_rune_alchemist", "fg": 595 },
          { "id": "rune_alchemist", "fg": 595 },
          { "id": "overlay_wielded_rune_animist", "fg": 596 },
          { "id": "rune_animist", "fg": 596 },
          { "id": "overlay_wielded_rune_biomancer", "fg": 597 },
          { "id": "rune_biomancer", "fg": 597 },
          { "id": "overlay_wielded_rune_druid", "fg": 598 },
          { "id": "rune_druid", "fg": 598 },
          { "id": "overlay_wielded_rune_earthshaper", "fg": 599 },
          { "id": "rune_earthshaper", "fg": 599 },
          { "id": "overlay_wielded_rune_kelvinist", "fg": 600 },
          { "id": "rune_kelvinist", "fg": 600 },
          { "id": "overlay_wielded_rune_magus", "fg": 601 },
          { "id": "rune_magus", "fg": 601 },
          { "id": "overlay_wielded_rune_stormshaper", "fg": 602 },
          { "id": "rune_stormshaper", "fg": 602 },
          { "id": "overlay_wielded_rune_technomancer", "fg": 603 },
          { "id": "rune_technomancer", "fg": 603 },
          { "id": "egg_owlbear", "fg": 604 },
          { "id": "overlay_wielded_egg_owlbear", "fg": 604 },
          { "id": "egg_owlbear_rock", "fg": 605 },
          { "id": "overlay_wielded_egg_owlbear_rock", "fg": 605 },
          { "id": "hairball", "fg": 606, "rotates": false },
          { "id": "overlay_wielded_hairball", "fg": 606, "rotates": false },
          { "id": "impure_meat", "fg": 607, "rotates": false },
          { "id": "overlay_wielded_impure_meat", "fg": 607, "rotates": false },
          { "id": "meat_dragon", "fg": 608, "rotates": false },
          { "id": "overlay_wielded_meat_dragon", "fg": 608, "rotates": false },
          { "id": "overlay_wielded_purified_meat", "fg": 609, "rotates": false },
          { "id": "purified_meat", "fg": 609, "rotates": false },
          { "id": "overlay_wielded_scream_mush", "fg": 610, "rotates": false },
          { "id": "scream_mush", "fg": 610, "rotates": false },
          { "id": "lizardfolk_trident", "fg": 611, "rotates": false },
          { "id": "overlay_wielded_lizardfolk_trident", "fg": 612, "rotates": false },
          { "id": "overlay_wielded_skewer", "fg": 613, "rotates": false },
          { "id": "skewer", "fg": 613, "bg": 3, "rotates": false },
          { "id": "fungicide", "fg": 614, "bg": 3, "rotates": false },
          { "id": "bag_holding_1", "fg": 615, "rotates": false },
          { "id": "overlay_wielded_bag_holding_1", "fg": 616, "rotates": false },
          { "id": "overlay_female_worn_bag_holding_1", "fg": 617, "rotates": false },
          { "id": "overlay_male_worn_bag_holding_1", "fg": 618, "rotates": false },
          { "id": "bag_holding_2", "fg": 619, "rotates": false },
          { "id": "overlay_wielded_bag_holding_2", "fg": 620, "rotates": false },
          { "id": "overlay_female_worn_bag_holding_2", "fg": 621, "rotates": false },
          { "id": "overlay_male_worn_bag_holding_2", "fg": 622, "rotates": false },
          { "id": "bag_holding_3", "fg": 623, "rotates": false },
          { "id": "overlay_wielded_bag_holding_3", "fg": 624, "rotates": false },
          { "id": "overlay_female_worn_bag_holding_3", "fg": 625, "rotates": false },
          { "id": "overlay_male_worn_bag_holding_3", "fg": 626, "rotates": false },
          { "id": "belt_haste", "fg": 627, "rotates": false },
          { "id": "overlay_wielded_belt_haste", "fg": 627, "rotates": false },
          { "id": "overlay_worn_belt_haste", "fg": 628, "rotates": false },
          { "id": "belt_str", "fg": 629, "rotates": false },
          { "id": "overlay_wielded_belt_str", "fg": 630, "rotates": false },
          { "id": "overlay_worn_belt_str", "fg": 630, "rotates": false },
          { "id": "debug_fireball_hammer", "fg": 631, "rotates": false },
          { "id": "overlay_wielded_debug_fireball_hammer", "fg": 632, "rotates": false },
          { "id": "magi_staff_minor", "fg": 633, "rotates": false },
          { "id": "overlay_wielded_magi_staff_minor", "fg": 634, "rotates": false },
          { "id": "overlay_wielded_wizard_hat", "fg": 635, "rotates": false },
          { "id": "wizard_hat", "fg": 635, "rotates": false },
          { "id": "mbelt_haste", "fg": 636, "rotates": false },
          { "id": "overlay_wielded_mbelt_haste", "fg": 636, "rotates": false },
          { "id": "overlay_worn_mbelt_haste", "fg": 637, "rotates": false },
          { "id": "mbelt_iron_whip", "fg": 638, "rotates": false },
          { "id": "overlay_wielded_mbelt_iron_whip", "fg": 638, "rotates": false },
          { "id": "overlay_worn_mbelt_iron_whip", "fg": 639, "rotates": false },
          { "id": "mbelt_pockets_greater", "fg": 640, "rotates": false },
          { "id": "overlay_wielded_mbelt_pockets_greater", "fg": 640, "rotates": false },
          { "id": "overlay_worn_mbelt_pockets_greater", "fg": 641, "rotates": false },
          { "id": "mbelt_pockets_lesser", "fg": 642, "rotates": false },
          { "id": "overlay_wielded_mbelt_pockets_lesser", "fg": 642, "rotates": false },
          { "id": "overlay_worn_mbelt_pockets_lesser", "fg": 643, "rotates": false },
          { "id": "mbelt_technomancer_toolbelt", "fg": 644, "rotates": false },
          { "id": "overlay_wielded_mbelt_technomancer_toolbelt", "fg": 644, "rotates": false },
          { "id": "overlay_worn_mbelt_technomancer_toolbelt", "fg": 645, "rotates": false },
          { "id": "mbelt_thor", "fg": 646, "rotates": false },
          { "id": "overlay_wielded_mbelt_thor", "fg": 646, "rotates": false },
          { "id": "overlay_worn_mbelt_thor", "fg": 647, "rotates": false },
          { "id": "mbelt_weaponry", "fg": 648, "rotates": false },
          { "id": "overlay_wielded_mbelt_weaponry", "fg": 648, "rotates": false },
          { "id": "overlay_worn_mbelt_weaponry", "fg": 649, "rotates": false },
          { "id": "mwhip_iron", "fg": 650, "rotates": false },
          { "id": "overlay_wielded_mwhip_iron", "fg": 651, "rotates": false },
          { "id": "mboots_escape", "fg": 652, "rotates": false },
          { "id": "overlay_wielded_mboots_escape", "fg": 652, "rotates": false },
          { "id": "overlay_worn_mboots_escape", "fg": 653, "rotates": false },
          { "id": "mboots_grounding", "fg": 654, "rotates": false },
          { "id": "overlay_wielded_mboots_grounding", "fg": 654, "rotates": false },
          { "id": "overlay_worn_mboots_grounding", "fg": 655, "rotates": false },
          { "id": "mboots_haste", "fg": 656, "rotates": false },
          { "id": "overlay_wielded_mboots_haste", "fg": 656, "rotates": false },
          { "id": "overlay_worn_mboots_haste", "fg": 657, "rotates": false },
          { "id": "mboots_sevenleague", "fg": 658, "rotates": false },
          { "id": "overlay_wielded_mboots_sevenleague", "fg": 658, "rotates": false },
          { "id": "overlay_worn_mboots_sevenleague", "fg": 659, "rotates": false },
          { "id": "mbracer_defense_greater", "fg": 660, "rotates": false },
          { "id": "overlay_wielded_mbracer_defense_greater", "fg": 660, "rotates": false },
          { "id": "overlay_worn_mbracer_defense_greater", "fg": 661, "rotates": false },
          { "id": "mbracer_defense_lesser", "fg": 662, "rotates": false },
          { "id": "overlay_wielded_mbracer_defense_lesser", "fg": 662, "rotates": false },
          { "id": "overlay_worn_mbracer_defense_lesser", "fg": 663, "rotates": false },
          { "id": "mbracer_lightning_greater", "fg": 664, "rotates": false },
          { "id": "overlay_wielded_mbracer_lightning_greater", "fg": 664, "rotates": false },
          { "id": "overlay_worn_mbracer_lightning_greater", "fg": 665, "rotates": false },
          { "id": "mbracer_lightning_lesser", "fg": 666, "rotates": false },
          { "id": "overlay_wielded_mbracer_lightning_lesser", "fg": 666, "rotates": false },
          { "id": "overlay_worn_mbracer_lightning_lesser", "fg": 667, "rotates": false },
          { "id": "mbracer_steel_pair", "fg": 668, "rotates": false },
          { "id": "overlay_wielded_mbracer_steel_pair", "fg": 668, "rotates": false },
          { "id": "overlay_worn_mbracer_steel_pair", "fg": 669, "rotates": false },
          { "id": "mbracer_steel_single", "fg": 670, "rotates": false },
          { "id": "overlay_wielded_mbracer_steel_single", "fg": 670, "rotates": false },
          { "id": "overlay_worn_mbracer_steel_single", "fg": 671, "rotates": false },
          { "id": "magic_suppressor", "fg": 672, "rotates": false },
          { "id": "overlay_wielded_magic_suppressor", "fg": 672, "rotates": false },
          { "id": "mana_dot_sight", "fg": 673, "rotates": false },
          { "id": "overlay_wielded_mana_dot_sight", "fg": 673, "rotates": false },
          { "id": "mana_laser_rail", "fg": 673, "rotates": false },
          { "id": "overlay_wielded_mana_laser_rail", "fg": 673, "rotates": false },
          { "id": "mana_laser_under", "fg": 673, "rotates": false },
          { "id": "overlay_wielded_mana_laser_under", "fg": 673, "rotates": false },
          { "id": "mmask_disappearance", "fg": 674, "rotates": false },
          { "id": "overlay_wielded_mmask_disappearance", "fg": 674, "rotates": false },
          { "id": "overlay_female_worn_mmask_disappearance", "fg": 685, "rotates": false },
          { "id": "overlay_male_worn_mmask_disappearance", "fg": 686, "rotates": false },
          { "id": "mmask_vision", "fg": 687, "rotates": false },
          { "id": "overlay_wielded_mmask_vision", "fg": 687, "rotates": false },
          { "id": "overlay_female_worn_mmask_vision", "fg": 688, "rotates": false },
          { "id": "overlay_male_worn_mmask_vision", "fg": 689, "rotates": false },
          { "id": "rune_animist_weapon", "fg": 690, "rotates": false },
          { "id": "overlay_wielded_rune_animist_weapon", "fg": 690, "rotates": false },
          { "id": "rune_biomancer_weapon", "fg": 691, "rotates": false },
          { "id": "overlay_wielded_rune_biomancer_weapon", "fg": 691, "rotates": false },
          { "id": "rune_kelvinist_weapon", "fg": 692, "rotates": false },
          { "id": "overlay_wielded_rune_kelvinist_weapon", "fg": 692, "rotates": false },
          { "id": "rune_magus_weapon", "fg": 693, "rotates": false },
          { "id": "overlay_wielded_rune_magus_weapon", "fg": 693, "rotates": false },
          { "id": "rune_stormshaper_weapon", "fg": 694, "rotates": false },
          { "id": "overlay_wielded_rune_stormshaper_weapon", "fg": 694, "rotates": false },
          { "id": "rune_technomancer_weapon", "fg": 695, "rotates": false },
          { "id": "overlay_wielded_rune_technomancer_weapon", "fg": 695, "rotates": false },
          { "id": "springstaff-extended", "fg": 696, "rotates": false },
          { "id": "overlay_wielded_springstaff-extended", "fg": 696, "rotates": false },
          { "id": "springstaff-retracted", "fg": 697, "rotates": false },
          { "id": "overlay_wielded_springstaff-retracted", "fg": 697, "rotates": false },
          { "id": "heat_cube", "fg": 698, "rotates": false },
          { "id": "overlay_wielded_heat_cube", "fg": 698, "rotates": false },
          { "id": "heat_cube_torch_on", "fg": 699, "rotates": false },
          { "id": "overlay_wielded_heat_cube_torch_on", "fg": 699, "rotates": false },
          { "id": "mflask_hip_whiskey", "fg": 700, "rotates": false },
          { "id": "overlay_wielded_mflask_hip_whiskey", "fg": 701, "rotates": false },
          { "id": "overlay_worn_mflask_hip_whiskey", "fg": 702, "rotates": false },
          { "id": "mkey_opening", "fg": 703, "rotates": false },
          { "id": "overlay_wielded_mkey_opening", "fg": 703, "rotates": false },
          { "id": "mspider_box", "fg": 704, "rotates": false },
          { "id": "overlay_wielded_mspider_box", "fg": 704, "rotates": false },
          { "id": "mtailors_kit", "fg": 705, "rotates": false },
          { "id": "overlay_wielded_mtailors_kit", "fg": 705, "rotates": false },
          { "id": "mtorch_everburning", "fg": 706, "rotates": false },
          { "id": "overlay_wielded_mtorch_everburning", "fg": 707, "rotates": false },
          { "id": "mtorch_everburning_lit", "fg": 708, "rotates": false },
          { "id": "overlay_wielded_mtorch_everburning_lit", "fg": 709, "rotates": false },
          { "id": "gunblade", "fg": 710, "rotates": false },
          { "id": "overlay_wielded_gunblade", "fg": 711, "rotates": false },
          { "id": "m47a1", "fg": 712, "rotates": false },
          { "id": "overlay_wielded_m47a1", "fg": 713, "rotates": false },
          { "id": "rune_druid_weapon", "fg": 714, "rotates": false },
          { "id": "overlay_wielded_rune_druid_weapon", "fg": 715, "rotates": false },
          { "id": "mring_blades_lesser", "fg": 716, "rotates": false },
          { "id": "overlay_wielded_mring_blades_lesser", "fg": 716, "rotates": false },
          { "id": "mring_copper", "fg": 717, "rotates": false },
          { "id": "overlay_wielded_mring_copper", "fg": 717, "rotates": false },
          { "id": "mring_dexterity_1", "fg": 718, "rotates": false },
          { "id": "overlay_wielded_mring_dexterity_1", "fg": 718, "rotates": false },
          { "id": "mring_dexterity_2", "fg": 719, "rotates": false },
          { "id": "overlay_wielded_mring_dexterity_2", "fg": 719, "rotates": false },
          { "id": "mring_dexterity_3", "fg": 720, "rotates": false },
          { "id": "overlay_wielded_mring_dexterity_3", "fg": 720, "rotates": false },
          { "id": "mring_dexterity_4", "fg": 721, "rotates": false },
          { "id": "overlay_wielded_mring_dexterity_4", "fg": 721, "rotates": false },
          { "id": "mring_dodge_bonus_1", "fg": 722, "rotates": false },
          { "id": "overlay_wielded_mring_dodge_bonus_1", "fg": 722, "rotates": false },
          { "id": "mring_dodge_bonus_2", "fg": 723, "rotates": false },
          { "id": "overlay_wielded_mring_dodge_bonus_2", "fg": 723, "rotates": false },
          { "id": "mring_gold", "fg": 724, "rotates": false },
          { "id": "overlay_wielded_mring_gold", "fg": 724, "rotates": false },
          { "id": "mring_intelligence_1", "fg": 725, "rotates": false },
          { "id": "overlay_wielded_mring_intelligence_1", "fg": 725, "rotates": false },
          { "id": "mring_intelligence_2", "fg": 726, "rotates": false },
          { "id": "overlay_wielded_mring_intelligence_2", "fg": 726, "rotates": false },
          { "id": "mring_intelligence_3", "fg": 727, "rotates": false },
          { "id": "overlay_wielded_mring_intelligence_3", "fg": 727, "rotates": false },
          { "id": "mring_intelligence_4", "fg": 728, "rotates": false },
          { "id": "overlay_wielded_mring_intelligence_4", "fg": 728, "rotates": false },
          { "id": "mring_perception_1", "fg": 729, "rotates": false },
          { "id": "overlay_wielded_mring_perception_1", "fg": 729, "rotates": false },
          { "id": "mring_perception_2", "fg": 730, "rotates": false },
          { "id": "overlay_wielded_mring_perception_2", "fg": 730, "rotates": false },
          { "id": "mring_perception_3", "fg": 731, "rotates": false },
          { "id": "overlay_wielded_mring_perception_3", "fg": 731, "rotates": false },
          { "id": "mring_perception_4", "fg": 732, "rotates": false },
          { "id": "overlay_wielded_mring_perception_4", "fg": 732, "rotates": false },
          { "id": "mring_platinum", "fg": 733, "rotates": false },
          { "id": "overlay_wielded_mring_platinum", "fg": 733, "rotates": false },
          { "id": "mring_protection_2", "fg": 734, "rotates": false },
          { "id": "overlay_wielded_mring_protection_2", "fg": 734, "rotates": false },
          { "id": "mring_protection_4", "fg": 735, "rotates": false },
          { "id": "overlay_wielded_mring_protection_4", "fg": 735, "rotates": false },
          { "id": "mring_protection_6", "fg": 736, "rotates": false },
          { "id": "overlay_wielded_mring_protection_6", "fg": 736, "rotates": false },
          { "id": "mring_protection_8", "fg": 737, "rotates": false },
          { "id": "overlay_wielded_mring_protection_8", "fg": 737, "rotates": false },
          { "id": "mring_silver", "fg": 738, "rotates": false },
          { "id": "overlay_wielded_mring_silver", "fg": 738, "rotates": false },
          { "id": "mring_speed_10", "fg": 739, "rotates": false },
          { "id": "overlay_wielded_mring_speed_10", "fg": 739, "rotates": false },
          { "id": "mring_speed_3", "fg": 740, "rotates": false },
          { "id": "overlay_wielded_mring_speed_3", "fg": 740, "rotates": false },
          { "id": "mring_speed_5", "fg": 741, "rotates": false },
          { "id": "overlay_wielded_mring_speed_5", "fg": 741, "rotates": false },
          { "id": "mring_speed_7", "fg": 742, "rotates": false },
          { "id": "overlay_wielded_mring_speed_7", "fg": 742, "rotates": false },
          { "id": "mring_strength_1", "fg": 743, "rotates": false },
          { "id": "overlay_wielded_mring_strength_1", "fg": 743, "rotates": false },
          { "id": "mring_strength_2", "fg": 744, "rotates": false },
          { "id": "overlay_wielded_mring_strength_2", "fg": 744, "rotates": false },
          { "id": "mring_strength_3", "fg": 745, "rotates": false },
          { "id": "overlay_wielded_mring_strength_3", "fg": 745, "rotates": false },
          { "id": "mring_strength_4", "fg": 746, "rotates": false },
          { "id": "overlay_wielded_mring_strength_4", "fg": 746, "rotates": false },
          { "id": "mtoken_arming_sword", "fg": 747, "rotates": false },
          { "id": "overlay_wielded_mtoken_arming_sword", "fg": 747, "rotates": false },
          { "id": "mtoken_battleaxe", "fg": 748, "rotates": false },
          { "id": "overlay_wielded_mtoken_battleaxe", "fg": 748, "rotates": false },
          { "id": "mtoken_broadsword", "fg": 749, "rotates": false },
          { "id": "overlay_wielded_mtoken_broadsword", "fg": 749, "rotates": false },
          { "id": "mtoken_crowbar", "fg": 750, "rotates": false },
          { "id": "overlay_wielded_mtoken_crowbar", "fg": 750, "rotates": false },
          { "id": "mtoken_hammer", "fg": 751, "rotates": false },
          { "id": "overlay_wielded_mtoken_hammer", "fg": 751, "rotates": false },
          { "id": "mtoken_longsword", "fg": 752, "rotates": false },
          { "id": "overlay_wielded_mtoken_longsword", "fg": 752, "rotates": false },
          { "id": "mtoken_mace", "fg": 753, "rotates": false },
          { "id": "overlay_wielded_mtoken_mace", "fg": 753, "rotates": false },
          { "id": "mtoken_pike", "fg": 754, "rotates": false },
          { "id": "overlay_wielded_mtoken_pike", "fg": 754, "rotates": false },
          { "id": "mtoken_q_staff", "fg": 755, "rotates": false },
          { "id": "overlay_wielded_mtoken_q_staff", "fg": 755, "rotates": false },
          { "id": "mtoken_screwdriver_set", "fg": 756, "rotates": false },
          { "id": "overlay_wielded_mtoken_screwdriver_set", "fg": 756, "rotates": false },
          { "id": "mtoken_toolbox", "fg": 757, "rotates": false },
          { "id": "overlay_wielded_mtoken_toolbox", "fg": 757, "rotates": false },
          { "id": "cestus_plus_one", "fg": 758, "bg": 5 },
          { "id": "overlay_wielded_cestus_plus_one", "fg": 758 },
          { "id": "cestus_plus_two", "fg": 759, "bg": 5 },
          { "id": "overlay_wielded_cestus_plus_two", "fg": 759 },
          { "id": "flaming_fist", "fg": 760, "rotates": false },
          { "id": "overlay_wielded_flaming_fist", "fg": 761, "rotates": false },
          { "id": "flaming_fist_plus_one", "fg": 762, "bg": 282 },
          { "id": "overlay_wielded_flaming_fist_plus_one", "fg": 761, "rotates": false },
          { "id": "flaming_fist_plus_two", "fg": 763, "bg": 282 },
          { "id": "overlay_wielded_flaming_fist_plus_two", "fg": 763 },
          { "id": "gauntlet_pounding", "fg": 764, "rotates": false },
          { "id": "overlay_wielded_gauntlet_pounding", "fg": 765, "rotates": false },
          { "id": "rune_earthshaper_weapon", "fg": 766, "rotates": false },
          { "id": "overlay_wielded_rune_earthshaper_weapon", "fg": 767, "rotates": false },
          { "id": "shotcestus", "fg": 768, "rotates": false },
          { "id": "overlay_wielded_shotcestus", "fg": 769, "rotates": false },
          { "id": "disp_wand", "fg": 770, "rotates": false },
          { "id": "overlay_wielded_disp_wand", "fg": 771, "rotates": false },
          { "id": "spell_wand", "fg": 772, "rotates": false },
          { "id": "overlay_wielded_spell_wand", "fg": 773, "rotates": false },
          { "id": "wand_cone_cold_greater", "fg": 774, "rotates": false },
          { "id": "overlay_wielded_wand_cone_cold_greater", "fg": 775, "rotates": false },
          { "id": "wand_cone_cold_lesser", "fg": 776, "rotates": false },
          { "id": "overlay_wielded_wand_cone_cold_lesser", "fg": 777, "rotates": false },
          { "id": "wand_cone_cold_minor", "fg": 778, "rotates": false },
          { "id": "overlay_wielded_wand_cone_cold_minor", "fg": 779, "rotates": false },
          { "id": "overlay_wielded_wand_disp_cone_cold_greater", "fg": 780, "rotates": false },
          { "id": "wand_disp_cone_cold_greater", "fg": 780, "rotates": false },
          { "id": "overlay_wielded_wand_disp_cone_cold_lesser", "fg": 781, "rotates": false },
          { "id": "wand_disp_cone_cold_lesser", "fg": 781, "rotates": false },
          { "id": "overlay_wielded_wand_disp_cone_cold_minor", "fg": 782, "rotates": false },
          { "id": "wand_disp_cone_cold_minor", "fg": 782, "rotates": false },
          { "id": "overlay_wielded_wand_disp_fireball_greater", "fg": 783, "rotates": false },
          { "id": "wand_disp_fireball_greater", "fg": 783, "rotates": false },
          { "id": "overlay_wielded_wand_disp_fireball_lesser", "fg": 784, "rotates": false },
          { "id": "wand_disp_fireball_lesser", "fg": 784, "rotates": false },
          { "id": "overlay_wielded_wand_disp_fireball_minor", "fg": 785, "rotates": false },
          { "id": "wand_disp_fireball_minor", "fg": 785, "rotates": false },
          { "id": "wand_disp_hoaryblast_greater", "fg": 786, "rotates": false },
          { "id": "overlay_wielded_wand_disp_hoaryblast_greater", "fg": 787, "rotates": false },
          { "id": "wand_disp_hoaryblast_lesser", "fg": 788, "rotates": false },
          { "id": "overlay_wielded_wand_disp_hoaryblast_lesser", "fg": 789, "rotates": false },
          { "id": "wand_disp_hoaryblast_minor", "fg": 790, "rotates": false },
          { "id": "overlay_wielded_wand_disp_hoaryblast_minor", "fg": 791, "rotates": false },
          { "id": "wand_disp_magic_missile_greater", "fg": 792, "rotates": false },
          { "id": "overlay_wielded_wand_disp_magic_missile_greater", "fg": 793, "rotates": false },
          { "id": "wand_disp_magic_missile_lesser", "fg": 794, "rotates": false },
          { "id": "overlay_wielded_wand_disp_magic_missile_lesser", "fg": 795, "rotates": false },
          { "id": "wand_disp_magic_missile_minor", "fg": 796, "rotates": false },
          { "id": "overlay_wielded_wand_disp_magic_missile_minor", "fg": 797, "rotates": false },
          { "id": "wand_disp_mana_beam_greater", "fg": 798, "rotates": false },
          { "id": "overlay_wielded_wand_disp_mana_beam_greater", "fg": 799, "rotates": false },
          { "id": "wand_disp_mana_beam_lesser", "fg": 800, "rotates": false },
          { "id": "overlay_wielded_wand_disp_mana_beam_lesser", "fg": 801, "rotates": false },
          { "id": "wand_disp_mana_beam_minor", "fg": 802, "rotates": false },
          { "id": "overlay_wielded_wand_disp_mana_beam_minor", "fg": 803, "rotates": false },
          { "id": "wand_disp_point_flare_greater", "fg": 804, "rotates": false },
          { "id": "overlay_wielded_wand_disp_point_flare_greater", "fg": 805, "rotates": false },
          { "id": "wand_disp_point_flare_lesser", "fg": 806, "rotates": false },
          { "id": "overlay_wielded_wand_disp_point_flare_lesser", "fg": 807, "rotates": false },
          { "id": "wand_disp_point_flare_minor", "fg": 808, "rotates": false },
          { "id": "overlay_wielded_wand_disp_point_flare_minor", "fg": 809, "rotates": false },
          { "id": "wand_fireball_greater", "fg": 810, "rotates": false },
          { "id": "overlay_wielded_wand_fireball_greater", "fg": 811, "rotates": false },
          { "id": "wand_fireball_lesser", "fg": 812, "rotates": false },
          { "id": "overlay_wielded_wand_fireball_lesser", "fg": 813, "rotates": false },
          { "id": "wand_fireball_minor", "fg": 814, "rotates": false },
          { "id": "overlay_wielded_wand_fireball_minor", "fg": 815, "rotates": false },
          { "id": "wand_hoaryblast_greater", "fg": 816, "rotates": false },
          { "id": "overlay_wielded_wand_hoaryblast_greater", "fg": 817, "rotates": false },
          { "id": "wand_hoaryblast_lesser", "fg": 818, "rotates": false },
          { "id": "overlay_wielded_wand_hoaryblast_lesser", "fg": 819, "rotates": false },
          { "id": "wand_hoaryblast_minor", "fg": 820, "rotates": false },
          { "id": "overlay_wielded_wand_hoaryblast_minor", "fg": 821, "rotates": false },
          { "id": "wand_magic_missile_greater", "fg": 822, "rotates": false },
          { "id": "overlay_wielded_wand_magic_missile_greater", "fg": 823, "rotates": false },
          { "id": "wand_magic_missile_lesser", "fg": 824, "rotates": false },
          { "id": "overlay_wielded_wand_magic_missile_lesser", "fg": 825, "rotates": false },
          { "id": "wand_magic_missile_minor", "fg": 826, "rotates": false },
          { "id": "overlay_wielded_wand_magic_missile_minor", "fg": 827, "rotates": false },
          { "id": "wand_mana_beam_greater", "fg": 828, "rotates": false },
          { "id": "overlay_wielded_wand_mana_beam_greater", "fg": 829, "rotates": false },
          { "id": "wand_mana_beam_lesser", "fg": 830, "rotates": false },
          { "id": "overlay_wielded_wand_mana_beam_lesser", "fg": 831, "rotates": false },
          { "id": "wand_mana_beam_minor", "fg": 832, "rotates": false },
          { "id": "overlay_wielded_wand_mana_beam_minor", "fg": 833, "rotates": false },
          { "id": "wand_point_flare_greater", "fg": 834, "rotates": false },
          { "id": "overlay_wielded_wand_point_flare_greater", "fg": 835, "rotates": false },
          { "id": "wand_point_flare_lesser", "fg": 836, "rotates": false },
          { "id": "overlay_wielded_wand_point_flare_lesser", "fg": 837, "rotates": false },
          { "id": "wand_point_flare_minor", "fg": 838, "rotates": false },
          { "id": "overlay_wielded_wand_point_flare_minor", "fg": 839, "rotates": false },
          { "id": "acid_res_aura", "fg": 3, "rotates": false },
          { "id": "overlay_wielded_acid_res_aura", "fg": 3, "rotates": false },
          { "id": "acid_res_aura_greater", "fg": 3, "rotates": false },
          { "id": "overlay_wielded_acid_res_aura_greater", "fg": 3, "rotates": false },
          { "id": "aura_stoneskin", "fg": 842, "rotates": false },
          { "id": "overlay_wielded_aura_stoneskin", "fg": 842, "rotates": false },
          { "id": "overlay_female_worn_aura_stoneskin", "fg": 843, "rotates": false },
          { "id": "overlay_male_worn_aura_stoneskin", "fg": 844, "rotates": false },
          { "id": "bonespear", "fg": 845, "rotates": true },
          { "id": "overlay_wielded_bonespear", "fg": 846, "rotates": true },
          { "id": "dragon_shell_black", "fg": 847, "rotates": false },
          { "id": "overlay_wielded_dragon_shell_black", "fg": 847, "rotates": false },
          {
            "id": "overlay_worn_dragon_shell_black",
            "fg": [
              { "weight": 30, "sprite": 848 },
              { "weight": 30, "sprite": 849 },
              { "weight": 30, "sprite": 850 },
              { "weight": 30, "sprite": 851 }
            ],
            "animated": true,
            "rotates": false
          },
          { "id": "druid_dust", "fg": 852, "rotates": false },
          { "id": "overlay_wielded_druid_dust", "fg": 852, "rotates": false },
          { "id": "druid_recurve", "fg": 853, "rotates": true },
          { "id": "overlay_wielded_druid_recurve", "fg": 854, "rotates": true },
          { "id": "druid_seed", "fg": 855, "rotates": false },
          { "id": "overlay_wielded_druid_seed", "fg": 855, "rotates": false },
          { "id": "finger_firelighter", "fg": 856 },
          { "id": "overlay_wielded_finger_firelighter", "fg": 857 },
          { "id": "fleshpouch", "fg": 858, "rotates": true },
          { "id": "overlay_wielded_fleshpouch", "fg": 858, "rotates": true },
          { "id": "overlay_worn_fleshpouch", "fg": 859, "rotates": true },
          { "id": "ice_gliders", "fg": 860, "rotates": false },
          { "id": "overlay_wielded_ice_gliders", "fg": 860, "rotates": false },
          { "id": "overlay_worn_ice_gliders", "fg": 861, "rotates": false },
          { "id": "magic_lamp", "fg": 862, "rotates": false },
          { "id": "magic_light", "fg": 863, "rotates": false },
          { "id": "obfuscating_aura", "fg": 864, "rotates": false },
          { "id": "overlay_wielded_obfuscating_aura", "fg": 864, "rotates": false },
          { "id": "overlay_wielded_shield_ice", "fg": 865, "rotates": false },
          { "id": "shield_ice", "fg": 865, "rotates": false },
          { "id": "overlay_worn_shield_ice", "fg": 866, "rotates": false },
          { "id": "stonefist", "fg": 867, "rotates": false },
          { "id": "overlay_wielded_stonefist", "fg": 868, "rotates": false },
          { "id": "stormglove", "fg": 869, "rotates": false },
          { "id": "overlay_wielded_stormglove", "fg": 870, "rotates": false },
          { "id": "stormhammer", "fg": 871, "rotates": false },
          { "id": "overlay_wielded_stormhammer", "fg": 872, "rotates": false },
          { "id": "tentacle_whip", "fg": 873, "rotates": true },
          { "id": "overlay_wielded_tentacle_whip", "fg": 874, "rotates": true },
          { "id": "crystallized_mana", "fg": 875, "rotates": false },
          { "id": "overlay_wielded_crystallized_mana", "fg": 875, "rotates": false },
          { "id": "overlay_wielded_small_mana_crystal", "fg": 876, "rotates": false },
          { "id": "small_mana_crystal", "fg": 876, "rotates": false },
          { "id": "gram", "fg": 877, "rotates": false },
          { "id": "overlay_wielded_gram", "fg": 878, "rotates": false },
          { "id": "gungnir", "fg": 879, "rotates": false },
          { "id": "laevateinn", "fg": 880, "rotates": false },
          { "id": "overlay_wielded_laevateinn", "fg": 881, "rotates": false },
          { "id": "mjolnir", "fg": 882, "bg": 3, "rotates": false },
          { "id": "overlay_wielded_mjolnir", "fg": 883, "rotates": false },
          { "id": "mithril_ingot", "fg": 884, "rotates": false },
          { "id": "overlay_wielded_mithril_ingot", "fg": 884, "rotates": false },
          { "id": "mithril_lump", "fg": 885, "rotates": false },
          { "id": "overlay_wielded_mithril_lump", "fg": 885, "rotates": false },
          { "id": "orichalcum_ingot", "fg": 886, "rotates": false },
          { "id": "overlay_wielded_orichalcum_ingot", "fg": 886, "rotates": false },
          { "id": "orichalcum_lump", "fg": 887, "rotates": false },
          { "id": "overlay_wielded_orichalcum_lump", "fg": 887, "rotates": false },
          { "id": "orichalcum_sliver", "fg": 888, "rotates": false },
          { "id": "overlay_wielded_orichalcum_sliver", "fg": 888, "rotates": false },
          { "id": "iv_black_dragon", "fg": 890, "rotates": false },
          { "id": "overlay_wielded_iv_black_dragon", "fg": 890, "rotates": false },
          { "id": "manatouched_serum", "fg": 889, "rotates": false },
          { "id": "overlay_wielded_manatouched_serum", "fg": 889, "rotates": false },
          { "id": "mutagen_black_dragon", "fg": 890, "rotates": false },
          { "id": "overlay_wielded_mutagen_black_dragon", "fg": 890, "rotates": false },
          { "id": "wand_fireball", "fg": 891, "rotates": false },
          { "id": "overlay_wielded_wand_fireball", "fg": 892, "rotates": false },
          { "id": "wand_magic_missile", "fg": 893, "rotates": false },
          { "id": "overlay_wielded_wand_magic_missile", "fg": 894, "rotates": false },
          { "id": "alchemy_basic", "fg": 895, "rotates": false },
          { "id": "overlay_wielded_alchemy_basic", "fg": 895, "rotates": false },
          { "id": "black_dragons", "fg": 896, "rotates": false },
          { "id": "overlay_wielded_black_dragons", "fg": 896, "rotates": false },
          { "id": "black_dragons_historical", "fg": 897, "rotates": false },
          { "id": "overlay_wielded_black_dragons_historical", "fg": 897, "rotates": false },
          { "id": "book_mythological", "fg": 898, "rotates": false },
          { "id": "overlay_wielded_book_mythological", "fg": 898, "rotates": false },
          { "id": "cooking_poison", "fg": 899, "rotates": false },
          { "id": "overlay_wielded_cooking_poison", "fg": 899, "rotates": false },
          { "id": "enchantment_basic", "fg": 900, "rotates": false },
          { "id": "overlay_wielded_enchantment_basic", "fg": 900, "rotates": false },
          { "id": "magic_armormaking", "fg": 901, "rotates": false },
          { "id": "overlay_wielded_magic_armormaking", "fg": 901, "rotates": false },
          { "id": "metal_legends", "fg": 902, "rotates": false },
          { "id": "overlay_wielded_metal_legends", "fg": 902, "rotates": false },
          { "id": "necro_basic", "fg": 903, "rotates": false },
          { "id": "overlay_wielded_necro_basic", "fg": 903, "rotates": false },
          { "id": "overlay_wielded_techno_basic", "fg": 904, "rotates": false },
          { "id": "techno_basic", "fg": 904, "rotates": false },
          { "id": "biomancer_spellbook", "fg": 905, "rotates": true },
          { "id": "overlay_wielded_biomancer_spellbook", "fg": 905, "rotates": true },
          { "id": "DEBUG_spellbook", "fg": 906, "rotates": false },
          { "id": "overlay_wielded_DEBUG_spellbook", "fg": 906, "rotates": false },
          { "id": "druid_spellbook", "fg": 907, "rotates": true },
          { "id": "overlay_wielded_druid_spellbook", "fg": 907, "rotates": true },
          { "id": "eshaper_spellbook", "fg": 908 },
          { "id": "overlay_wielded_eshaper_spellbook", "fg": 908 },
          { "id": "generic_spellbook", "fg": 909, "rotates": false },
          { "id": "overlay_wielded_generic_spellbook", "fg": 909, "rotates": false },
          { "id": "light_manipulation_spellbook", "fg": 910, "rotates": false },
          { "id": "overlay_wielded_light_manipulation_spellbook", "fg": 910, "rotates": false },
          { "id": "magus_spellbook", "fg": 911 },
          { "id": "overlay_wielded_magus_spellbook", "fg": 911 },
          { "id": "magus_spellbook_move", "fg": 912 },
          { "id": "overlay_wielded_magus_spellbook_move", "fg": 912 },
          { "id": "novice_stormshaper_book", "fg": 913, "rotates": false },
          { "id": "overlay_wielded_novice_stormshaper_book", "fg": 913, "rotates": false },
          { "id": "overlay_wielded_priest_advanced", "fg": 914, "rotates": false },
          { "id": "priest_advanced", "fg": 914, "rotates": false },
          { "id": "overlay_wielded_priest_beginner", "fg": 915, "rotates": false },
          { "id": "priest_beginner", "fg": 915, "rotates": false },
          { "id": "overlay_wielded_pyro", "fg": 916, "rotates": false },
          { "id": "pyro", "fg": 916, "rotates": false },
          { "id": "overlay_wielded_recovery_spellbook", "fg": 917, "rotates": false },
          { "id": "recovery_spellbook", "fg": 917, "rotates": false },
          { "id": "overlay_wielded_stat_up_spellbook", "fg": 918 },
          { "id": "stat_up_spellbook", "fg": 918 },
          { "id": "overlay_wielded_summon_scroll_smudged", "fg": 919 },
          { "id": "summon_scroll_smudged", "fg": 919 },
          { "id": "overlay_wielded_summon_undead_spellbook", "fg": 920 },
          { "id": "summon_undead_spellbook", "fg": 920 },
          { "id": "overlay_wielded_techno_em", "fg": 921 },
          { "id": "techno_em", "fg": 921 },
          { "id": "overlay_wielded_techno_fundamentals", "fg": 922 },
          { "id": "techno_fundamentals", "fg": 922 },
          { "id": "overlay_wielded_techno_idiots", "fg": 923 },
          { "id": "techno_idiots", "fg": 923 },
          { "id": "overlay_wielded_tome_of_storms", "fg": 924, "rotates": false },
          { "id": "tome_of_storms", "fg": 924, "rotates": false },
          { "id": "overlay_wielded_translocate_spellbook", "fg": 925 },
          { "id": "translocate_spellbook", "fg": 925 },
          { "id": "overlay_wielded_winter_grasp", "fg": 926, "rotates": true },
          { "id": "winter_grasp", "fg": 926, "rotates": true },
          { "id": "overlay_wielded_wizard_advanced", "fg": 927, "rotates": true },
          { "id": "wizard_advanced", "fg": 927, "rotates": true },
          { "id": "overlay_wielded_wizard_beginner", "fg": 928, "rotates": true },
          { "id": "wizard_beginner", "fg": 928, "rotates": true },
          { "id": "overlay_wielded_wizard_utility", "fg": 929, "rotates": true },
          { "id": "wizard_utility", "fg": 929, "rotates": true },
          { "id": "lightning_storm_scroll", "fg": 930, "rotates": false },
          { "id": "overlay_wielded_lightning_storm_scroll", "fg": 930, "rotates": false },
          {
            "id": [
              "overlay_wielded_spell_scroll",
              "overlay_wielded_spell_scroll_baleful_polymorph",
              "overlay_wielded_spell_scroll_boneclub",
              "overlay_wielded_spell_scroll_caustic_aura",
              "overlay_wielded_spell_scroll_feralform",
              "overlay_wielded_spell_scroll_flamebreath",
              "overlay_wielded_spell_scroll_flamesword",
              "overlay_wielded_spell_scroll_impactsling",
              "overlay_wielded_spell_scroll_improved_knock",
              "overlay_wielded_spell_scroll_knifeshot",
              "overlay_wielded_spell_scroll_knock",
              "overlay_wielded_spell_scroll_overcharge_eyes",
              "overlay_wielded_spell_scroll_repelling_arc",
              "overlay_wielded_spell_scroll_summon_floating_disk",
              "overlay_wielded_spell_scroll_tornskin"
            ],
            "fg": 930,
            "rotates": false
          },
          {
            "id": [
              "spell_scroll",
              "spell_scroll_baleful_polymorph",
              "spell_scroll_boneclub",
              "spell_scroll_caustic_aura",
              "spell_scroll_feralform",
              "spell_scroll_flamebreath",
              "spell_scroll_flamesword",
              "spell_scroll_impactsling",
              "spell_scroll_improved_knock",
              "spell_scroll_knifeshot",
              "spell_scroll_knock",
              "spell_scroll_overcharge_eyes",
              "spell_scroll_repelling_arc",
              "spell_scroll_summon_floating_disk",
              "spell_scroll_tornskin"
            ],
            "fg": 930,
            "rotates": false
          },
          { "id": "overlay_wielded_spell_scroll_acid_resistance", "fg": 930, "rotates": false },
          { "id": "spell_scroll_acid_resistance", "fg": 930, "rotates": false },
          { "id": "overlay_wielded_spell_scroll_animated_blade", "fg": 930, "rotates": false },
          { "id": "spell_scroll_animated_blade", "fg": 930, "rotates": false },
          { "id": "overlay_wielded_spell_scroll_biomancer_coagulant_weave", "fg": 930, "rotates": false },
          { "id": "spell_scroll_biomancer_coagulant_weave", "fg": 930, "rotates": false },
          { "id": "overlay_wielded_spell_scroll_biomancer_paralytic_dart", "fg": 930, "rotates": false },
          { "id": "spell_scroll_biomancer_paralytic_dart", "fg": 930, "rotates": false },
          { "id": "overlay_wielded_spell_scroll_biomancer_visceral_projection", "fg": 930, "rotates": false },
          { "id": "spell_scroll_biomancer_visceral_projection", "fg": 930, "rotates": false },
          { "id": "overlay_wielded_spell_scroll_bio_acidicspray", "fg": 930, "rotates": false },
          { "id": "spell_scroll_bio_acidicspray", "fg": 930, "rotates": false },
          { "id": "overlay_wielded_spell_scroll_bio_bonespear", "fg": 930, "rotates": false },
          { "id": "spell_scroll_bio_bonespear", "fg": 930, "rotates": false },
          { "id": "overlay_wielded_spell_scroll_bio_fleshpouch", "fg": 930, "rotates": false },
          { "id": "spell_scroll_bio_fleshpouch", "fg": 930, "rotates": false },
          { "id": "overlay_wielded_spell_scroll_bio_grotesque", "fg": 930, "rotates": false },
          { "id": "spell_scroll_bio_grotesque", "fg": 930, "rotates": false },
          { "id": "overlay_wielded_spell_scroll_bless", "fg": 930, "rotates": false },
          { "id": "spell_scroll_bless", "fg": 930, "rotates": false },
          { "id": "overlay_wielded_spell_scroll_blinding_flash", "fg": 930, "rotates": false },
          { "id": "spell_scroll_blinding_flash", "fg": 930, "rotates": false },
          { "id": "overlay_wielded_spell_scroll_burning_hands", "fg": 930, "rotates": false },
          { "id": "spell_scroll_burning_hands", "fg": 930, "rotates": false },
          { "id": "overlay_wielded_spell_scroll_cats_grace", "fg": 930, "rotates": false },
          { "id": "spell_scroll_cats_grace", "fg": 930, "rotates": false },
          { "id": "overlay_wielded_spell_scroll_chilling_touch", "fg": 930, "rotates": false },
          { "id": "spell_scroll_chilling_touch", "fg": 930, "rotates": false },
          { "id": "overlay_wielded_spell_scroll_clairvoyance", "fg": 930, "rotates": false },
          { "id": "spell_scroll_clairvoyance", "fg": 930, "rotates": false },
          { "id": "overlay_wielded_spell_scroll_cone_cold", "fg": 930, "rotates": false },
          { "id": "spell_scroll_cone_cold", "fg": 930, "rotates": false },
          { "id": "overlay_wielded_spell_scroll_create_atomic_lamp", "fg": 930, "rotates": false },
          { "id": "spell_scroll_create_atomic_lamp", "fg": 930, "rotates": false },
          { "id": "overlay_wielded_spell_scroll_create_atomic_light", "fg": 930, "rotates": false },
          { "id": "spell_scroll_create_atomic_light", "fg": 930, "rotates": false },
          { "id": "overlay_wielded_spell_scroll_create_lighter", "fg": 930, "rotates": false },
          { "id": "spell_scroll_create_lighter", "fg": 930, "rotates": false },
          { "id": "overlay_wielded_spell_scroll_crystallize_mana", "fg": 930, "rotates": false },
          { "id": "spell_scroll_crystallize_mana", "fg": 930, "rotates": false },
          { "id": "overlay_wielded_spell_scroll_dark_sight", "fg": 930, "rotates": false },
          { "id": "spell_scroll_dark_sight", "fg": 930, "rotates": false },
          { "id": "overlay_wielded_spell_scroll_druidic_healing", "fg": 930, "rotates": false },
          { "id": "spell_scroll_druidic_healing", "fg": 930, "rotates": false },
          { "id": "overlay_wielded_spell_scroll_druidic_regrowth", "fg": 930, "rotates": false },
          { "id": "spell_scroll_druidic_regrowth", "fg": 930, "rotates": false },
          { "id": "overlay_wielded_spell_scroll_druid_naturebow1", "fg": 930, "rotates": false },
          { "id": "spell_scroll_druid_naturebow1", "fg": 930, "rotates": false },
          { "id": "overlay_wielded_spell_scroll_druid_rootstrike", "fg": 930, "rotates": false },
          { "id": "spell_scroll_druid_rootstrike", "fg": 930, "rotates": false },
          { "id": "overlay_wielded_spell_scroll_druid_veggrasp", "fg": 930, "rotates": false },
          { "id": "spell_scroll_druid_veggrasp", "fg": 930, "rotates": false },
          { "id": "overlay_wielded_spell_scroll_druid_woodshaft", "fg": 930, "rotates": false },
          { "id": "spell_scroll_druid_woodshaft", "fg": 930, "rotates": false },
          { "id": "overlay_wielded_spell_scroll_eagles_sight", "fg": 930, "rotates": false },
          { "id": "spell_scroll_eagles_sight", "fg": 930, "rotates": false },
          { "id": "overlay_wielded_spell_scroll_earthshaper_pillar", "fg": 930, "rotates": false },
          { "id": "spell_scroll_earthshaper_pillar", "fg": 930, "rotates": false },
          { "id": "overlay_wielded_spell_scroll_earthshaper_stoneskin", "fg": 930, "rotates": false },
          { "id": "spell_scroll_earthshaper_stoneskin", "fg": 930, "rotates": false },
          { "id": "overlay_wielded_spell_scroll_eshaper_piercing_bolt", "fg": 930, "rotates": false },
          { "id": "spell_scroll_eshaper_piercing_bolt", "fg": 930, "rotates": false },
          { "id": "overlay_wielded_spell_scroll_eshaper_rockbolt", "fg": 930, "rotates": false },
          { "id": "spell_scroll_eshaper_rockbolt", "fg": 930, "rotates": false },
          { "id": "overlay_wielded_spell_scroll_eshaper_shardspray", "fg": 930, "rotates": false },
          { "id": "spell_scroll_eshaper_shardspray", "fg": 930, "rotates": false },
          { "id": "overlay_wielded_spell_scroll_eshaper_shardstorm", "fg": 930, "rotates": false },
          { "id": "spell_scroll_eshaper_shardstorm", "fg": 930, "rotates": false },
          { "id": "overlay_wielded_spell_scroll_ethereal_grasp", "fg": 930, "rotates": false },
          { "id": "spell_scroll_ethereal_grasp", "fg": 930, "rotates": false },
          { "id": "overlay_wielded_spell_scroll_fireball", "fg": 930, "rotates": false },
          { "id": "spell_scroll_fireball", "fg": 930, "rotates": false },
          { "id": "overlay_wielded_spell_scroll_foxs_cunning", "fg": 930, "rotates": false },
          { "id": "spell_scroll_foxs_cunning", "fg": 930, "rotates": false },
          { "id": "overlay_wielded_spell_scroll_freezing_touch", "fg": 930, "rotates": false },
          { "id": "spell_scroll_freezing_touch", "fg": 930, "rotates": false },
          { "id": "overlay_wielded_spell_scroll_frost_armor", "fg": 930, "rotates": false },
          { "id": "spell_scroll_frost_armor", "fg": 930, "rotates": false },
          { "id": "overlay_wielded_spell_scroll_frost_spray", "fg": 930, "rotates": false },
          { "id": "spell_scroll_frost_spray", "fg": 930, "rotates": false },
          { "id": "overlay_wielded_spell_scroll_glide_ice", "fg": 930, "rotates": false },
          { "id": "spell_scroll_glide_ice", "fg": 930, "rotates": false },
          { "id": "overlay_wielded_spell_scroll_gravity_well", "fg": 930, "rotates": false },
          { "id": "spell_scroll_gravity_well", "fg": 930, "rotates": false },
          { "id": "overlay_wielded_spell_scroll_hoary_blast", "fg": 930, "rotates": false },
          { "id": "spell_scroll_hoary_blast", "fg": 930, "rotates": false },
          { "id": "overlay_wielded_spell_scroll_holographic_transposition", "fg": 930, "rotates": false },
          { "id": "spell_scroll_holographic_transposition", "fg": 930, "rotates": false },
          { "id": "overlay_wielded_spell_scroll_holy_blade", "fg": 930, "rotates": false },
          { "id": "spell_scroll_holy_blade", "fg": 930, "rotates": false },
          { "id": "overlay_wielded_spell_scroll_ice_shield", "fg": 930, "rotates": false },
          { "id": "spell_scroll_ice_shield", "fg": 930, "rotates": false },
          { "id": "overlay_wielded_spell_scroll_ice_spike", "fg": 930, "rotates": false },
          { "id": "spell_scroll_ice_spike", "fg": 930, "rotates": false },
          { "id": "overlay_wielded_spell_scroll_invisibility", "fg": 930, "rotates": false },
          { "id": "spell_scroll_invisibility", "fg": 930, "rotates": false },
          { "id": "overlay_wielded_spell_scroll_jolt", "fg": 930, "rotates": false },
          { "id": "spell_scroll_jolt", "fg": 930, "rotates": false },
          { "id": "overlay_wielded_spell_scroll_lava_bomb", "fg": 930, "rotates": false },
          { "id": "spell_scroll_lava_bomb", "fg": 930, "rotates": false },
          { "id": "overlay_wielded_spell_scroll_laze", "fg": 930, "rotates": false },
          { "id": "spell_scroll_laze", "fg": 930, "rotates": false },
          { "id": "overlay_wielded_spell_scroll_lightning_blast", "fg": 930, "rotates": false },
          { "id": "spell_scroll_lightning_blast", "fg": 930, "rotates": false },
          { "id": "overlay_wielded_spell_scroll_lightning_bolt", "fg": 930, "rotates": false },
          { "id": "spell_scroll_lightning_bolt", "fg": 930, "rotates": false },
          { "id": "overlay_wielded_spell_scroll_light_healing", "fg": 930, "rotates": false },
          { "id": "spell_scroll_light_healing", "fg": 930, "rotates": false },
          { "id": "overlay_wielded_spell_scroll_magic_missile", "fg": 930, "rotates": false },
          { "id": "spell_scroll_magic_missile", "fg": 930, "rotates": false },
          { "id": "overlay_wielded_spell_scroll_magus_escape", "fg": 930, "rotates": false },
          { "id": "spell_scroll_magus_escape", "fg": 930, "rotates": false },
          { "id": "overlay_wielded_spell_scroll_magus_haste", "fg": 930, "rotates": false },
          { "id": "spell_scroll_magus_haste", "fg": 930, "rotates": false },
          { "id": "overlay_wielded_spell_scroll_magus_mana_beam", "fg": 930, "rotates": false },
          { "id": "spell_scroll_magus_mana_beam", "fg": 930, "rotates": false },
          { "id": "overlay_wielded_spell_scroll_magus_mana_blast", "fg": 930, "rotates": false },
          { "id": "spell_scroll_magus_mana_blast", "fg": 930, "rotates": false },
          { "id": "overlay_wielded_spell_scroll_magus_mana_bolt", "fg": 930, "rotates": false },
          { "id": "spell_scroll_magus_mana_bolt", "fg": 930, "rotates": false },
          { "id": "overlay_wielded_spell_scroll_megablast", "fg": 930, "rotates": false },
          { "id": "spell_scroll_megablast", "fg": 930, "rotates": false },
          { "id": "overlay_wielded_spell_scroll_mirror_image", "fg": 930, "rotates": false },
          { "id": "spell_scroll_mirror_image", "fg": 930, "rotates": false },
          { "id": "overlay_wielded_spell_scroll_necrotic_gaze", "fg": 930, "rotates": false },
          { "id": "spell_scroll_necrotic_gaze", "fg": 930, "rotates": false },
          { "id": "overlay_wielded_spell_scroll_nova_flare", "fg": 930, "rotates": false },
          { "id": "spell_scroll_nova_flare", "fg": 930, "rotates": false },
          { "id": "overlay_wielded_spell_scroll_obfuscated_body", "fg": 930, "rotates": false },
          { "id": "spell_scroll_obfuscated_body", "fg": 930, "rotates": false },
          { "id": "overlay_wielded_spell_scroll_ogres_strength", "fg": 930, "rotates": false },
          { "id": "spell_scroll_ogres_strength", "fg": 930, "rotates": false },
          { "id": "overlay_wielded_spell_scroll_pain_split", "fg": 930, "rotates": false },
          { "id": "spell_scroll_pain_split", "fg": 930, "rotates": false },
          { "id": "overlay_wielded_spell_scroll_phase_door", "fg": 930, "rotates": false },
          { "id": "spell_scroll_phase_door", "fg": 930, "rotates": false },
          { "id": "overlay_wielded_spell_scroll_point_flare", "fg": 930, "rotates": false },
          { "id": "spell_scroll_point_flare", "fg": 930, "rotates": false },
          { "id": "overlay_wielded_spell_scroll_protection_aura", "fg": 930, "rotates": false },
          { "id": "spell_scroll_protection_aura", "fg": 930, "rotates": false },
          { "id": "overlay_wielded_spell_scroll_purification_seed", "fg": 930, "rotates": false },
          { "id": "spell_scroll_purification_seed", "fg": 930, "rotates": false },
          { "id": "overlay_wielded_spell_scroll_quantum_tunnel_lesser", "fg": 930, "rotates": false },
          { "id": "spell_scroll_quantum_tunnel_lesser", "fg": 930, "rotates": false },
          { "id": "overlay_wielded_spell_scroll_recover_bionic_power", "fg": 930, "rotates": false },
          { "id": "spell_scroll_recover_bionic_power", "fg": 930, "rotates": false },
          { "id": "overlay_wielded_spell_scroll_recover_fatigue", "fg": 930, "rotates": false },
          { "id": "spell_scroll_recover_fatigue", "fg": 930, "rotates": false },
          { "id": "overlay_wielded_spell_scroll_recover_mana", "fg": 930, "rotates": false },
          { "id": "spell_scroll_recover_mana", "fg": 930, "rotates": false },
          { "id": "overlay_wielded_spell_scroll_recover_pain", "fg": 930, "rotates": false },
          { "id": "spell_scroll_recover_pain", "fg": 930, "rotates": false },
          { "id": "overlay_wielded_spell_scroll_recover_stamina", "fg": 930, "rotates": false },
          { "id": "spell_scroll_recover_stamina", "fg": 930, "rotates": false },
          { "id": "overlay_wielded_spell_scroll_seismic_stomp", "fg": 930, "rotates": false },
          { "id": "spell_scroll_seismic_stomp", "fg": 930, "rotates": false },
          { "id": "overlay_wielded_spell_scroll_animated_blade", "fg": 930, "rotates": false },
          { "id": "spell_scroll_animated_blade", "fg": 930, "rotates": false },
          { "id": "overlay_wielded_spell_scroll_summon_magic_motorcycle", "fg": 930, "rotates": false },
          { "id": "spell_scroll_summon_magic_motorcycle", "fg": 930, "rotates": false },
          { "id": "overlay_wielded_spell_scroll_smite", "fg": 930, "rotates": false },
          { "id": "spell_scroll_smite", "fg": 930, "rotates": false },
          { "id": "overlay_wielded_spell_scroll_spirit_armor", "fg": 930, "rotates": false },
          { "id": "spell_scroll_spirit_armor", "fg": 930, "rotates": false },
          { "id": "overlay_wielded_spell_scroll_stonefist", "fg": 930, "rotates": false },
          { "id": "spell_scroll_stonefist", "fg": 930, "rotates": false },
          { "id": "overlay_wielded_spell_scroll_stormshaper_ionization", "fg": 930, "rotates": false },
          { "id": "spell_scroll_stormshaper_ionization", "fg": 930, "rotates": false },
          { "id": "overlay_wielded_spell_scroll_stormshaper_wall_of_fog", "fg": 930, "rotates": false },
          { "id": "spell_scroll_stormshaper_wall_of_fog", "fg": 930, "rotates": false },
          { "id": "overlay_wielded_spell_scroll_storm_hammer", "fg": 930, "rotates": false },
          { "id": "spell_scroll_storm_hammer", "fg": 930, "rotates": false },
          { "id": "overlay_wielded_spell_scroll_summon_cats", "fg": 930, "rotates": false },
          { "id": "spell_scroll_summon_cats", "fg": 930, "rotates": false },
          { "id": "overlay_wielded_spell_scroll_summon_decayed_pouncer", "fg": 930, "rotates": false },
          { "id": "spell_scroll_summon_decayed_pouncer", "fg": 930, "rotates": false },
          { "id": "overlay_wielded_spell_scroll_bio_bonespear", "fg": 930, "rotates": false },
          { "id": "spell_scroll_bio_bonespear", "fg": 930, "rotates": false },
          { "id": "overlay_wielded_spell_scroll_summon_skeleton", "fg": 930, "rotates": false },
          { "id": "spell_scroll_summon_skeleton", "fg": 930, "rotates": false },
          { "id": "overlay_wielded_spell_scroll_summon_wisps", "fg": 930, "rotates": false },
          { "id": "spell_scroll_summon_wisps", "fg": 930, "rotates": false },
          { "id": "overlay_wielded_spell_scroll_summon_wolf", "fg": 930, "rotates": false },
          { "id": "spell_scroll_summon_wolf", "fg": 930, "rotates": false },
          { "id": "overlay_wielded_spell_scroll_summon_zombie", "fg": 930, "rotates": false },
          { "id": "spell_scroll_summon_zombie", "fg": 930, "rotates": false },
          { "id": "overlay_wielded_spell_scroll_synaptic_stimulation", "fg": 930, "rotates": false },
          { "id": "spell_scroll_synaptic_stimulation", "fg": 930, "rotates": false },
          { "id": "overlay_wielded_spell_scroll_taze", "fg": 930, "rotates": false },
          { "id": "spell_scroll_taze", "fg": 930, "rotates": false },
          { "id": "overlay_wielded_spell_scroll_vicious_tentacle", "fg": 930, "rotates": false },
          { "id": "spell_scroll_vicious_tentacle", "fg": 930, "rotates": false },
          { "id": "overlay_wielded_spell_scroll_windrun", "fg": 930, "rotates": false },
          { "id": "spell_scroll_windrun", "fg": 930, "rotates": false },
          { "id": "overlay_wielded_spell_scroll_windstrike", "fg": 930, "rotates": false },
          { "id": "spell_scroll_windstrike", "fg": 930, "rotates": false },
          { "id": "overlay_wielded_spell_scroll_x-ray", "fg": 930, "rotates": false },
          { "id": "spell_scroll_x-ray", "fg": 930, "rotates": false },
          { "id": "cauldron_demon_chitin", "fg": 931, "rotates": false },
          { "id": "overlay_wielded_cauldron_demon_chitin", "fg": 932, "rotates": false },
          { "id": "cauldron_orichalcum", "fg": 933, "rotates": false },
          { "id": "overlay_wielded_cauldron_orichalcum", "fg": 934, "rotates": false },
          { "id": "demon_forge", "fg": 935, "rotates": false },
          { "id": "overlay_wielded_demon_forge", "fg": 936, "rotates": false },
          { "id": "overlay_wielded_sewing_kit", "fg": 937, "rotates": false },
          { "id": "sewing_kit", "fg": 937, "rotates": false },
          { "id": "overlay_wielded_tailors_kit", "fg": 938 },
          { "id": "tailors_kit", "fg": 938 },
          { "id": "fold_orichalcum_frame", "fg": 939, "rotates": false },
          { "id": "overlay_wielded_fold_orichalcum_frame", "fg": 940, "rotates": false },
          { "id": "orichalcum_frame", "fg": 941, "rotates": false },
          { "id": "overlay_wielded_orichalcum_frame", "fg": 942, "rotates": false },
          { "id": "lizardfolk_club", "fg": 943, "rotates": false },
          { "id": "overlay_wielded_lizardfolk_club", "fg": 944, "rotates": false },
          { "id": "lizardfolk_javelin", "fg": 945, "rotates": false },
          { "id": "overlay_wielded_lizardfolk_javelin", "fg": 946, "rotates": false },
          { "id": "lizardfolk_javelin_gun", "fg": 947, "rotates": false },
          { "id": "overlay_wielded_lizardfolk_javelin_gun", "fg": 947, "rotates": false },
          { "id": "novice_kelvin_spellbook", "fg": 948, "rotates": false },
          { "id": "novice_earth_spellbook", "fg": 949, "rotates": false },
          { "id": "novice_storm_spellbook", "fg": 950, "rotates": false },
          { "id": "cestus", "fg": 951, "bg": 3, "rotates": false },
          { "id": "mana", "fg": 952, "rotates": false },
          { "id": "overlay_wielded_mana", "fg": 952, "rotates": false }
        ],
        "//": "range 513 to 1280",
        "sprite_width": 32,
        "sprite_height": 32,
        "sprite_offset_x": 0,
        "sprite_offset_y": 0
      },
      {
        "file": "MagicalNights_Monsters.png",
        "tiles": [
          { "id": "mon_demon_spider", "fg": 1281, "bg": 4, "rotates": false },
          { "id": "corpse_mon_demon_spider", "fg": 1282, "rotates": false },
          { "id": "mon_demon_spiderling", "fg": 1283, "bg": 4, "rotates": false },
          { "id": "corpse_mon_demon_spiderling", "fg": 1284, "rotates": false },
          { "id": "mon_dragon_black_wyrmling", "fg": 1285, "bg": 4, "rotates": false },
          { "id": "corpse_mon_dragon_black_wyrmling", "fg": 1286, "rotates": false },
          { "id": "mon_forgedemons", "fg": 1287, "bg": 4, "rotates": false },
          { "id": "corpse_mon_forgedemons", "fg": 1288, "rotates": false },
          {
            "id": "mon_forgedwarves",
            "fg": [
              { "weight": 3, "sprite": 1289 },
              { "weight": 3, "sprite": 1290 },
              { "weight": 3, "sprite": 1291 },
              { "weight": 3, "sprite": 1292 },
              { "weight": 3, "sprite": 1296 },
              { "weight": 3, "sprite": 1297 },
              { "weight": 3, "sprite": 1298 },
              { "weight": 3, "sprite": 1299 }
            ],
            "bg": 2,
            "rotates": false
          },
          { "id": "mon_mirror_image", "fg": 1293 },
          { "id": "mon_yulecat_cub", "fg": 1294, "bg": 4, "rotates": false },
          { "id": "corpse_mon_yulecat_cub", "fg": 1295, "rotates": false },
          { "id": "mon_forgemaster1", "fg": 1296, "bg": 2, "rotates": false },
          { "id": "corpse_mon_forgedwarves", "fg": 1300, "rotates": false },
          { "id": "corpse_mon_forgemaster1", "fg": 1300, "rotates": false },
          {
            "id": "mon_goblin_chieftain",
            "fg": [
              { "weight": 3, "sprite": 1302 },
              { "weight": 3, "sprite": 1303 },
              { "weight": 3, "sprite": 1304 },
              { "weight": 3, "sprite": 1305 },
              { "weight": 3, "sprite": 1306 },
              { "weight": 3, "sprite": 1307 }
            ],
            "bg": 2,
            "rotates": false
          },
          { "id": "corpse_mon_goblin_chieftain", "fg": 1308, "rotates": false },
          {
            "id": "mon_goblin_slinger",
            "fg": [
              { "weight": 3, "sprite": 1309 },
              { "weight": 3, "sprite": 1310 },
              { "weight": 3, "sprite": 1311 },
              { "weight": 3, "sprite": 1312 },
              { "weight": 3, "sprite": 1313 },
              { "weight": 3, "sprite": 1314 }
            ],
            "bg": 2,
            "rotates": false
          },
          { "id": "corpse_mon_goblin_slinger", "fg": 1315, "rotates": false },
          {
            "id": "mon_goblin_warrior",
            "fg": [
              { "weight": 3, "sprite": 1316 },
              { "weight": 3, "sprite": 1317 },
              { "weight": 3, "sprite": 1318 },
              { "weight": 3, "sprite": 1319 },
              { "weight": 3, "sprite": 1320 },
              { "weight": 3, "sprite": 1321 }
            ],
            "bg": 2,
            "rotates": false
          },
          { "id": "corpse_mon_goblin_warrior", "fg": 1322, "rotates": false },
          { "id": "mon_leprechaun", "fg": 1323, "bg": 4, "rotates": false },
          { "id": "corpse_mon_leprechaun", "fg": 1324, "rotates": false },
          { "id": "mon_workshop_elf", "fg": 1325, "bg": 4, "rotates": false },
          { "id": "corpse_mon_workshop_elf", "fg": 1326, "rotates": false },
          { "id": "mon_crocodile", "fg": 1327, "rotates": false },
          { "id": "corpse_mon_crocodile", "fg": 1328, "rotates": false },
          { "id": "mon_baleful_polymorph_frog", "fg": 1329, "bg": 1, "rotates": false },
          { "id": "corpse_mon_baleful_polymorph_frog", "fg": 1330, "rotates": false },
          { "id": "mon_black_pudding", "fg": 1331, "rotates": false },
          { "id": "mon_krabgek", "fg": 1332, "bg": 4, "rotates": false },
          { "id": "corpse_mon_krabgek", "fg": 1333, "rotates": false },
          { "id": "mon_lemure", "fg": 1334, "bg": 4, "rotates": false },
          { "id": "corpse_mon_lemure", "fg": 1335, "rotates": false },
          { "id": "mon_loup_garou", "fg": 1336, "bg": 4 },
          { "id": "mon_owlbear", "fg": 1337 },
          { "id": "corpse_mon_owlbear", "fg": 1338 },
          { "id": "mon_owlbear_cub", "fg": 1339 },
          { "id": "corpse_mon_owlbear_cub", "fg": 1340 },
          { "id": "mon_winter_wolf", "fg": 1341, "bg": 4, "rotates": false },
          { "id": "corpse_mon_winter_wolf", "fg": 1342, "rotates": false },
          { "id": "mon_shrieker", "fg": 1343, "bg": 4, "rotates": false },
          { "id": "corpse_mon_shrieker", "fg": 1344, "rotates": false },
          { "id": "mon_stirge", "fg": 1345, "rotates": false },
          { "id": "corpse_mon_stirge", "fg": 1346, "rotates": false },
          {
            "id": "mon_wisp",
            "fg": [
              { "weight": 3, "sprite": 1347 },
              { "weight": 3, "sprite": 1348 },
              { "weight": 3, "sprite": 1349 },
              { "weight": 3, "sprite": 1350 }
            ]
          },
          { "id": "mon_animated_blade", "fg": 1351 },
          {
            "id": "mon_orc_archer",
            "fg": [
              { "weight": 3, "sprite": 1352 },
              { "weight": 3, "sprite": 1353 },
              { "weight": 3, "sprite": 1354 },
              { "weight": 3, "sprite": 1355 },
              { "weight": 3, "sprite": 1356 },
              { "weight": 3, "sprite": 1357 }
            ],
            "bg": 4,
            "rotates": false
          },
          { "id": "corpse_mon_orc_archer", "fg": 1358, "rotates": false },
          {
            "id": "mon_orc_blood_warrior",
            "fg": [
              { "weight": 3, "sprite": 1359 },
              { "weight": 3, "sprite": 1360 },
              { "weight": 3, "sprite": 1361 },
              { "weight": 3, "sprite": 1362 },
              { "weight": 3, "sprite": 1363 },
              { "weight": 3, "sprite": 1364 }
            ],
            "bg": 4,
            "rotates": false
          },
          { "id": "corpse_mon_orc_blood_warrior", "fg": 1365, "rotates": false },
          {
            "id": "mon_orc_warrior",
            "fg": [
              { "weight": 3, "sprite": 1366 },
              { "weight": 3, "sprite": 1367 },
              { "weight": 3, "sprite": 1368 },
              { "weight": 3, "sprite": 1369 },
              { "weight": 3, "sprite": 1370 },
              { "weight": 3, "sprite": 1371 }
            ],
            "bg": 4,
            "rotates": false
          },
          { "id": "corpse_mon_orc_warrior", "fg": 1372, "rotates": false },
          { "id": "mon_were_zolf", "fg": 1373, "bg": 4 },
          { "id": "mon_zorc", "fg": 1374, "bg": 4 },
          { "id": "corpse_mon_zorc", "fg": 1375, "rotates": false },
          { "id": "broken_claygolem", "fg": 1376, "rotates": false },
          { "id": "overlay_wielded_broken_claygolem", "fg": 1376, "rotates": false },
          { "id": "broken_irongolem", "fg": 1377, "rotates": false },
          { "id": "overlay_wielded_broken_irongolem", "fg": 1377, "rotates": false },
          { "id": "broken_plasticgolem", "fg": 1378, "rotates": false },
          { "id": "overlay_wielded_broken_plasticgolem", "fg": 1378, "rotates": false },
          { "id": "broken_stonegolem", "fg": 1379, "rotates": false },
          { "id": "overlay_wielded_broken_stonegolem", "fg": 1379, "rotates": false },
          { "id": "broken_resingolem_fresh", "fg": 1380, "rotates": false },
          { "id": "overlay_wielded_broken_resingolem_fresh", "fg": 1380, "rotates": false },
          { "id": "broken_resingolem_half", "fg": 1381, "rotates": false },
          { "id": "overlay_wielded_broken_resingolem_half", "fg": 1381, "rotates": false },
          { "id": "broken_resingolem_cured", "fg": 1382, "rotates": false },
          { "id": "overlay_wielded_broken_resingolem_cured", "fg": 1382, "rotates": false }
        ],
        "//": "range 1281 to 1536",
        "sprite_width": 32,
        "sprite_height": 32,
        "sprite_offset_x": 0,
        "sprite_offset_y": 0
      },
      {
        "file": "MagicalNights_normal_offset.png",
        "tiles": [ { "id": "overlay_worn_wizard_hat", "fg": 1537, "rotates": false } ],
        "//": "range 1537 to 1552",
        "sprite_width": 32,
        "sprite_height": 32,
        "sprite_offset_x": 0,
        "sprite_offset_y": -16
      },
      {
        "file": "MagicalNights_large.png",
        "tiles": [
          { "id": "bg_big_dirt", "fg": 1553, "rotates": false },
          { "id": "bg_big_golem_shadow", "fg": 1554, "rotates": false },
          { "id": "bg_big_large_shadow", "fg": 1556, "rotates": false },
          { "id": "bg_big_normal_shadow", "fg": 1556, "rotates": false },
          { "id": "bg_big_snow", "fg": 1557, "rotates": false },
          { "id": "bg_big_tall_shadow", "fg": 1558, "rotates": false },
          { "id": "f_alembic", "fg": 1559, "rotates": false },
          {
            "id": "f_everburning_candelabra",
            "fg": [ { "weight": 11, "sprite": 1560 }, { "weight": 11, "sprite": 1561 }, { "weight": 11, "sprite": 1562 } ],
            "rotates": false,
            "animated": true
          },
          { "id": "f_glow_boulder", "fg": 1563, "rotates": false },
          { "id": "f_glow_boulder_season_autumn", "fg": 1564, "rotates": false },
          { "id": "f_glow_boulder_season_spring", "fg": 1565, "rotates": false },
          { "id": "f_glow_boulder_season_summer", "fg": 1566, "rotates": false },
          { "id": "f_glow_boulder_season_winter", "fg": 1567, "rotates": false },
          { "id": "f_huge_mana_crystal", "fg": 1568, "rotates": false },
          { "id": "overlay_worn_magic_lamp", "fg": 1569, "rotates": false },
          { "id": "overlay_worn_magic_light", "fg": 1570, "rotates": false },
          { "id": "overlay_wielded_gungnir", "fg": 1571, "rotates": false },
          {
            "id": [
              "magic_academy_ground",
              "magic_academy_2nd",
              "magic_academy_3rd",
              "magic_academy_4th",
              "magic_academy_5th",
              "magic_academy_6th",
              "magic_academy_7th",
              "magic_academy_8th"
            ],
            "fg": 1572,
            "rotates": false
          },
          { "id": "mon_demon_spider_queen", "fg": 1573, "rotates": false },
          { "id": "corpse_mon_demon_spider_queen", "fg": 1574, "rotates": false },
          { "id": "mon_dragon_black_young", "fg": 1575, "rotates": false },
          { "id": "corpse_mon_dragon_black_young", "fg": 1576, "rotates": false },
          { "id": "mon_forgeborn", "fg": 1577, "bg": 1558, "rotates": false },
          { "id": "corpse_mon_forgeborn", "fg": 1578, "rotates": false },
          { "id": "mon_claygolem", "fg": 1579, "bg": 1554, "rotates": false },
          { "id": "mon_irongolem", "fg": 1580, "bg": 1554, "rotates": false },
          { "id": "mon_plasticgolem", "fg": 1581, "bg": 1554, "rotates": false },
          { "id": "mon_stonegolem", "fg": 1582, "bg": 1554, "rotates": false },
          { "id": "mon_yulecat", "fg": 1583, "bg": 1555, "rotates": false },
          { "id": "corpse_mon_yulecat", "fg": 1584, "rotates": false },
          { "id": "mon_lizardfolk_chieftan", "fg": 1585, "rotates": false },
          { "id": "corpse_mon_lizardfolk_chieftan", "fg": 1586, "rotates": false },
          { "id": "mon_lizardfolk_hunter", "fg": 1587, "rotates": false },
          { "id": "corpse_mon_lizardfolk_hunter", "fg": 1588, "rotates": false },
          { "id": "mon_lizardfolk_shaman", "fg": 1589, "rotates": false },
          { "id": "corpse_mon_lizardfolk_shaman", "fg": 1590, "rotates": false },
          { "id": "mon_lizardfolk_warrior", "fg": 1591, "rotates": false },
          { "id": "corpse_mon_lizardfolk_warrior", "fg": 1592, "rotates": false },
          { "id": "mon_bulette", "fg": 1593, "rotates": false },
          { "id": "corpse_mon_bulette", "fg": 1594, "rotates": false },
          { "id": "mon_ogre", "fg": 1595, "rotates": false },
          { "id": "corpse_mon_ogre", "fg": 1596, "rotates": false },
          { "id": "mon_troll", "fg": 1597, "rotates": false },
          { "id": "corpse_mon_troll", "fg": 1598, "rotates": false },
          {
            "id": "t_thconc_floor_echandelier",
            "fg": [ { "weight": 11, "sprite": 1599 }, { "weight": 11, "sprite": 1600 }, { "weight": 11, "sprite": 1601 } ],
            "bg": 1602,
            "rotates": false,
            "animated": true
          },
          { "id": "t_tree_burnt", "fg": 1603, "bg": 1553, "rotates": false },
          { "id": "t_tree_burnt_season_autumn", "fg": 1604, "bg": 1553, "rotates": false },
          { "id": "t_tree_burnt_season_spring", "fg": 1605, "bg": 1553, "rotates": false },
          { "id": "t_tree_burnt_season_summer", "fg": 1606, "bg": 1553, "rotates": false },
          { "id": "t_tree_burnt_season_winter", "fg": 1607, "bg": 1557, "rotates": false },
          { "id": "mon_resingolem_fresh", "fg": 1608, "rotates": false },
          { "id": "mon_resingolem_half", "fg": 1609, "rotates": false },
          { "id": "mon_resingolem_cured", "fg": 1610, "rotates": false }
        ],
        "//": "range 1553 to 1680",
        "sprite_width": 64,
        "sprite_height": 80,
        "sprite_offset_x": -16,
        "sprite_offset_y": -48
      },
      {
        "file": "MagicalNights_huge.png",
        "tiles": [
          { "id": "f_orrery", "fg": 1681, "rotates": false },
          { "id": "mon_dragon_black_adult", "fg": 1682, "rotates": false },
          { "id": "corpse_mon_dragon_black_adult", "fg": 1683, "rotates": false }
        ],
        "//": "range 1681 to 1696",
        "sprite_width": 160,
        "sprite_height": 128,
        "sprite_offset_x": -48,
        "sprite_offset_y": -48
      }
    ]
  }
]
