[
  {
    "id": "emergency_book",
    "type": "BOOK",
    "copy-from": "base_book",
    "name": { "str": "Guide to Advanced Emergency Care", "str_pl": "copies of Guide to Advanced Emergency Care" },
    "description": "A thick textbook for paramedics describing advanced lifesaving procedures and field-expedient care methods.",
    "weight": "2063 g",
    "volume": "2 L",
    "price": "92 USD",
    "price_postapoc": "15 USD",
    "bashing": 8,
    "color": "blue",
    "skill": "firstaid",
    "required_level": 5,
    "max_level": 8,
    "intelligence": 10,
    "time": "55 m",
    "fun": -1
  },
  {
    "id": "mag_firstaid",
    "type": "BOOK",
    "copy-from": "base_book",
    "name": { "str": "Paramedics", "str_pl": "issues of Paramedics" },
    "description": "An educational magazine for EMTs.",
    "weight": "60 g",
    "volume": "250 ml",
    "price": "480 cent",
    "price_postapoc": "250 cent",
    "color": "pink",
    "skill": "firstaid",
    "max_level": 1,
    "intelligence": 1,
    "time": "8 m",
    "fun": 1
  },
  {
    "id": "manual_first_aid",
    "type": "BOOK",
    "copy-from": "base_book",
    "name": { "str": "The Big Book of First Aid", "str_pl": "copies of The Big Book of First Aid" },
    "description": "It's big and heavy, but full of great information about first aid.",
    "weight": "500 g",
    "volume": "1250 ml",
    "price": "25 USD",
    "price_postapoc": "1250 cent",
    "color": "green",
    "skill": "firstaid",
    "max_level": 3,
    "intelligence": 7,
    "time": "20 m"
  },
  {
    "id": "pocket_firstaid",
    "type": "BOOK",
    "copy-from": "base_book",
    "name": { "str": "Pocket Guide to First Aid", "str_pl": "copies of Pocket Guide to First Aid" },
    "description": "This pocket-sized leather-bound guide to first aid combines a wealth of concise information with simple to follow instructions and easy to read illustrations.",
    "weight": "192 g",
    "volume": "250 ml",
    "price": "40 USD",
    "price_postapoc": "750 cent",
    "material": [ "paper", "leather" ],
    "color": "green",
    "skill": "firstaid",
    "max_level": 2,
    "intelligence": 6,
    "time": "20 m"
  },
  {
    "id": "textbook_firstaid",
    "type": "BOOK",
    "copy-from": "base_book",
    "name": { "str": "First Responder Handbook", "str_pl": "copies of First Responder Handbook" },
    "//": "College-level textbooks are Cheap at $60.  Med book is likely more expensive.",
    "description": "A hardbound book detailing advanced first aid techniques and field-expedient medical care.",
    "weight": "1360 g",
    "volume": "2 L",
    "price": "85 USD",
    "price_postapoc": "1250 cent",
    "bashing": 4,
    "color": "blue",
    "skill": "firstaid",
    "required_level": 3,
    "max_level": 6,
    "intelligence": 8,
    "time": "30 m"
  },
  {
    "id": "booklet_firstaid",
    "type": "BOOK",
    "copy-from": "base_book",
    "name": { "str": "First Aid Kit Instruction Booklet", "str_pl": "copies of First Aid Kit Instruction Booklet" },
    "description": "Illustrated how-to guide for your first aid kit.",
    "weight": "60 g",
    "volume": "250 ml",
    "price": "480 cent",
    "price_postapoc": "50 cent",
    "color": "pink",
    "skill": "firstaid",
    "max_level": 1,
    "time": "8 m",
    "fun": 1
  },
  {
    "id": "reference_firstaid1",
    "type": "BOOK",
    "copy-from": "base_book",
    "name": { "str": "Physicians' Desk Reference", "str_pl": "copies of Physicians' Desk Reference" },
    "description": "This hefty volume contains all the legally mandated information relevant to physicians for writing prescriptions, generously supported by the efforts and contributions of major pharmaceutical companies.  At least it doesn't need power to be used, unlike digital pharmaceutical references like Medisoft.",
    "weight": "2268 g",
    "volume": "500 ml",
    "price": "100 USD",
    "price_postapoc": "2250 cent",
    "bashing": 7,
    "color": "blue",
    "intelligence": 12,
    "skill": "firstaid",
    "required_level": 6,
    "max_level": 10,
    "time": "30 m",
    "fun": -2
  },
  {
    "id": "reference_firstaid2",
    "type": "BOOK",
    "copy-from": "base_book",
    "name": { "str": "Merck Veterinary Manual", "str_pl": "copies of Merck Veterinary Manual" },
    "description": "This expansive text covers 'all domestic species and diseases in veterinary medicine worldwide'.  Should you need information regarding zoonotic diseases, off-label use of medication for animals, common dysfunctions and diseases of animals, or any other veterinary reference info, this is your book.",
    "weight": "5790 g",
    "volume": "500 ml",
    "price": "80 USD",
    "price_postapoc": "750 cent",
    "bashing": 7,
    "color": "blue",
    "skill": "firstaid",
    "required_level": 2,
    "max_level": 5,
    "intelligence": 9,
    "time": "30 m"
  }
]
